{"assets":{"7203CA2CE230D6DFACC528958CF7C285":{"type":"texture","index":3,"url":{"native":"assets\/0DED23A0-3417-418D-A749-38A8EE2281D1.pdf"},"width":913,"height":501},"968CA7F03E8F1452C105F26D19933736":{"type":"texture","index":5,"url":{"native":"assets\/0DED23A0-3417-418D-A749-38A8EE2281D1.pdf"},"width":775,"height":43},"F9A0A76BAF2A9879A1DAA8312FE7E552":{"type":"texture","index":0,"url":{"native":"assets\/0DED23A0-3417-418D-A749-38A8EE2281D1.pdf"},"width":1920,"height":1080},"B677092A5C2F6FCF6CE7E2A154347C83":{"type":"texture","index":4,"url":{"native":"assets\/0DED23A0-3417-418D-A749-38A8EE2281D1.pdf"},"width":632,"height":50},"7F2F06C91810C43EB3771BF2188F303E":{"type":"texture","index":2,"url":{"native":"assets\/0DED23A0-3417-418D-A749-38A8EE2281D1.pdf"},"width":913,"height":569},"DD72240AB455A2760B6508DF0985BD38":{"type":"texture","index":6,"url":{"native":"assets\/0DED23A0-3417-418D-A749-38A8EE2281D1.pdf"},"width":776,"height":48},"34C4F3867BF19FFC7B3A9911BD63353D":{"type":"texture","index":1,"url":{"native":"assets\/0DED23A0-3417-418D-A749-38A8EE2281D1.pdf"},"width":929,"height":569},"E46FF30837A55F9CB3342795BC784F21":{"type":"texture","index":8,"url":{"native":"assets\/0DED23A0-3417-418D-A749-38A8EE2281D1.pdf"},"width":1920,"height":1080},"C6AA0A31C6E0D3FCC48F42F06797D8CF":{"type":"texture","index":7,"url":{"native":"assets\/0DED23A0-3417-418D-A749-38A8EE2281D1.pdf"},"width":1920,"height":1080}},"events":[{"effects":[{"beginTime":0,"baseLayer":{"animations":[],"initialState":{"affineTransform":[1,0,0,1,0,0],"masksToBounds":false,"rotation":0,"scale":1,"position":{"pointX":523.18983459472656,"pointY":220.03970336914057},"width":632,"sublayerTransform":[1,0,0,0,0,1,0,0,0,0,1,0,0,0,0,1],"contentsRect":{"y":0,"x":0,"width":1,"height":1},"opacity":1,"edgeAntialiasingMask":251658240,"height":50,"hidden":false,"anchorPoint":{"pointX":0.5,"pointY":0.5}},"objectID":"D19386EA-EAAF-409A-8BF1-31A36E6B159C","layers":[{"animations":[],"initialState":{"affineTransform":[1,0,0,1,0,0],"masksToBounds":false,"rotation":0,"scale":1,"position":{"pointX":752.81016540527344,"pointY":344.96029663085943},"width":632,"sublayerTransform":[1,0,0,0,0,1,0,0,0,0,1,-0.00035007912466775983,0,0,0,1],"contentsRect":{"y":0,"x":0,"width":1,"height":1},"opacity":1,"edgeAntialiasingMask":251658240,"height":50,"hidden":false,"anchorPoint":{"pointX":1.191155325008344,"pointY":6.8992059326171891}},"layers":[{"animations":[{"additive":false,"timeOffset":0,"beginTime":1e-100,"repeatCount":0,"fillMode":"both","duration":0.5,"autoreverses":false,"animations":[{"repeatCount":0,"removedOnCompletion":true,"from":{"scalar":0},"timingFunction":"EaseInEaseOut","additive":false,"timeOffset":0,"autoreverses":false,"property":"opacity","fillMode":"both","duration":0.5,"beginTime":0,"to":{"scalar":1}},{"additive":false,"timeOffset":0,"beginTime":0,"from":{"scalar":false},"repeatCount":0,"fillMode":"forwards","duration":0.5,"autoreverses":false,"property":"hidden","to":{"scalar":false},"removedOnCompletion":true}],"removedOnCompletion":false}],"layers":[],"texturedRectangle":{"singleTextureOpacity":1,"textXHeight":0,"shapePath":{"lineWidth":1,"flatness":0.59999999999999998,"lineCapStyle":0,"elements":[{"type":"MoveToPoint","points":[[3.6898345947265625,3.5397033691405682]]},{"type":"AddLine","points":[[628.26271057128906,3.5397033691405682]]},{"type":"AddLine","points":[[628.26271057128906,46.383338928222656]]},{"type":"AddLine","points":[[3.6898345947265625,46.383338928222656]]},{"type":"CloseSubpath"},{"type":"MoveToPoint","points":[[3.6898345947265625,3.5397033691405682]]}],"windingRule":0,"lineJoinStyle":0,"miterLimit":10},"isBackgroundTexture":true,"textBaseline":0,"isVerticalText":false,"textureType":5},"initialState":{"affineTransform":[1,0,0,1,0,0],"masksToBounds":false,"rotation":0,"scale":1,"position":{"pointX":314.81016540527344,"pointY":23.960296630859432},"width":632,"sublayerTransform":[1,0,0,0,0,1,0,0,0,0,1,0,0,0,0,1],"contentsRect":{"y":0,"x":0,"width":1,"height":1},"opacity":1,"edgeAntialiasingMask":0,"height":50,"hidden":true,"anchorPoint":{"pointX":0.5,"pointY":0.5}},"texture":"B677092A5C2F6FCF6CE7E2A154347C83"}]}]},"effects":[],"duration":0.5,"type":"buildIn","attributes":{"direction":0},"name":"apple:dissolve character","objectID":"D19386EA-EAAF-409A-8BF1-31A36E6B159C"}],"automaticPlay":false,"hyperlinks":[],"accessibility":[{"text":"    bool try_push (const T& v)","targetRectangle":{"y":25.822231292724609,"x":985.666259765625,"width":504.08203125,"height":34}},{"text":"    {","targetRectangle":{"y":59.822231292724609,"x":985.666259765625,"width":84.013671875,"height":34}},{"text":"        size_t current_tail = tail.load();","targetRectangle":{"y":93.822231292724609,"x":985.666259765625,"width":705.71484375,"height":34}},{"text":"        size_t current_head = head.load();","targetRectangle":{"y":127.82223129272461,"x":985.666259765625,"width":705.71484375,"height":34}},{"text":"        size_t size = current_tail - current_head;","targetRectangle":{"y":195.82223129272461,"x":985.666259765625,"width":840.13671875,"height":34}},{"text":"        if (size >= (capacity - 1)) \/\/ full","targetRectangle":{"y":263.82223129272461,"x":985.666259765625,"width":722.517578125,"height":34}},{"text":"            return false;","targetRectangle":{"y":297.82223129272461,"x":985.666259765625,"width":420.068359375,"height":34}},{"text":"        size_t index = current_tail & (capacity - 1);","targetRectangle":{"y":365.82223129272461,"x":985.666259765625,"width":890.544921875,"height":34}},{"text":"        data[index] = v;","targetRectangle":{"y":399.82223129272461,"x":985.666259765625,"width":403.265625,"height":34}},{"text":"        tail.store (current_tail + 1);","targetRectangle":{"y":433.82223129272461,"x":985.666259765625,"width":638.50390625,"height":34}},{"text":"        return true;","targetRectangle":{"y":501.82223129272461,"x":985.666259765625,"width":336.0546875,"height":34}},{"text":"    }","targetRectangle":{"y":535.82223129272461,"x":985.666259765625,"width":84.013671875,"height":34}},{"text":"template<typename T>","targetRectangle":{"y":27.725105285644531,"x":50.132045745849609,"width":336.0546875,"height":34}},{"text":"class drow_queue_v2","targetRectangle":{"y":61.725105285644531,"x":50.132045745849609,"width":319.251953125,"height":34}},{"text":"{","targetRectangle":{"y":95.725105285644531,"x":50.132045745849609,"width":16.802734375,"height":34}},{"text":"public:","targetRectangle":{"y":129.72510528564453,"x":50.132045745849609,"width":117.619140625,"height":34}},{"text":"    drow_queue_v2 (size_t capacity_)","targetRectangle":{"y":163.72510528564453,"x":50.132045745849609,"width":604.8984375,"height":34}},{"text":"        : capacity (std::bit_ceil (capacity_))","targetRectangle":{"y":197.72510528564453,"x":50.132045745849609,"width":772.92578125,"height":34}},{"text":"    {}","targetRectangle":{"y":231.72510528564453,"x":50.132045745849609,"width":100.81640625,"height":34}},{"text":"    bool try_push (const T&);","targetRectangle":{"y":299.72510528564453,"x":50.132045745849609,"width":487.279296875,"height":34}},{"text":"    bool try_pop (T&);","targetRectangle":{"y":333.72510528564453,"x":50.132045745849609,"width":369.66015625,"height":34}},{"text":"private:","targetRectangle":{"y":401.72510528564453,"x":50.132045745849609,"width":134.421875,"height":34}},{"text":"    size_t capacity = 0;","targetRectangle":{"y":435.72510528564453,"x":50.132045745849609,"width":403.265625,"height":34}},{"text":"    std::vector<T> data { std::vector<T> (capacity) };","targetRectangle":{"y":469.72510528564453,"x":50.132045745849609,"width":907.34765625,"height":34}},{"text":"    std::atomic<size_t> head { 0 }, tail { 0 };","targetRectangle":{"y":503.72510528564453,"x":50.132045745849609,"width":789.728515625,"height":34}},{"text":"};","targetRectangle":{"y":537.72510528564453,"x":50.132045745849609,"width":33.60546875,"height":34}},{"text":"    bool try_pop (T& v)","targetRectangle":{"y":593.4832763671875,"x":985.666259765625,"width":386.462890625,"height":34}},{"text":"    {","targetRectangle":{"y":627.4832763671875,"x":985.666259765625,"width":84.013671875,"height":34}},{"text":"        size_t current_head = head.load();","targetRectangle":{"y":661.4832763671875,"x":985.666259765625,"width":705.71484375,"height":34}},{"text":"        size_t current_tail = tail.load();","targetRectangle":{"y":695.4832763671875,"x":985.666259765625,"width":705.71484375,"height":34}},{"text":"        if (current_head == current_tail) \/\/ empty","targetRectangle":{"y":763.4832763671875,"x":985.666259765625,"width":840.13671875,"height":34}},{"text":"            return false;","targetRectangle":{"y":797.4832763671875,"x":985.666259765625,"width":420.068359375,"height":34}},{"text":"        size_t index = current_head & (capacity - 1);","targetRectangle":{"y":865.4832763671875,"x":985.666259765625,"width":890.544921875,"height":34}},{"text":"        v = data[index];","targetRectangle":{"y":899.4832763671875,"x":985.666259765625,"width":403.265625,"height":34}},{"text":"        head.store(current_head + 1);","targetRectangle":{"y":933.4832763671875,"x":985.666259765625,"width":621.701171875,"height":34}},{"text":"        return true;","targetRectangle":{"y":1001.4832763671875,"x":985.666259765625,"width":336.0546875,"height":34}},{"text":"    }","targetRectangle":{"y":1035.4832763671875,"x":985.666259765625,"width":84.013671875,"height":34}}],"baseLayer":{"animations":[],"initialState":{"affineTransform":[1,0,0,1,0,0],"masksToBounds":false,"rotation":0,"scale":1,"position":{"pointX":960,"pointY":540},"width":1920,"sublayerTransform":[1,0,0,0,0,1,0,0,0,0,1,0,0,0,0,1],"contentsRect":{"y":0,"x":0,"width":1,"height":1},"opacity":1,"edgeAntialiasingMask":251658240,"height":1080,"hidden":false,"anchorPoint":{"pointX":0.5,"pointY":0.5}},"layers":[{"animations":[],"initialState":{"affineTransform":[1,0,0,1,0,0],"masksToBounds":false,"rotation":0,"scale":1,"position":{"pointX":960,"pointY":540},"width":1920,"sublayerTransform":[1,0,0,0,0,1,0,0,0,0,1,0,0,0,0,1],"contentsRect":{"y":0,"x":0,"width":1,"height":1},"opacity":1,"edgeAntialiasingMask":251658240,"height":1080,"hidden":false,"anchorPoint":{"pointX":0.5,"pointY":0.5}},"layers":[{"animations":[],"initialState":{"affineTransform":[1,0,0,1,0,0],"masksToBounds":false,"rotation":0,"scale":1,"position":{"pointX":960,"pointY":540},"width":1920,"sublayerTransform":[1,0,0,0,0,1,0,0,0,0,1,0,0,0,0,1],"contentsRect":{"y":0,"x":0,"width":1,"height":1},"opacity":1,"edgeAntialiasingMask":251658240,"height":1080,"hidden":false,"anchorPoint":{"pointX":0.5,"pointY":0.5}},"layers":[{"animations":[],"layers":[],"texturedRectangle":{"isBackgroundTexture":true,"singleTextureOpacity":1,"textureType":1,"textBaseline":0,"textXHeight":0,"isVerticalText":false},"initialState":{"affineTransform":[1,0,0,1,0,0],"masksToBounds":false,"rotation":0,"scale":1,"position":{"pointX":960,"pointY":540},"width":1920,"sublayerTransform":[1,0,0,0,0,1,0,0,0,0,1,0,0,0,0,1],"contentsRect":{"y":0,"x":0,"width":1,"height":1},"opacity":1,"edgeAntialiasingMask":0,"height":1080,"hidden":false,"anchorPoint":{"pointX":0.5,"pointY":0.5}},"texture":"F9A0A76BAF2A9879A1DAA8312FE7E552"}]}]},{"animations":[],"initialState":{"affineTransform":[1,0,0,1,0,0],"masksToBounds":false,"rotation":0,"scale":1,"position":{"pointX":960,"pointY":540},"width":1920,"sublayerTransform":[1,0,0,0,0,1,0,0,0,0,1,0,0,0,0,1],"contentsRect":{"y":0,"x":0,"width":1,"height":1},"opacity":1,"edgeAntialiasingMask":251658240,"height":1080,"hidden":false,"anchorPoint":{"pointX":0.5,"pointY":0.5}},"layers":[{"animations":[],"initialState":{"affineTransform":[1,0,0,1,0,0],"masksToBounds":false,"rotation":0,"scale":1,"position":{"pointX":510.63204574584961,"pointY":308.22510528564453},"width":929,"sublayerTransform":[1,0,0,0,0,1,0,0,0,0,1,0,0,0,0,1],"contentsRect":{"y":0,"x":0,"width":1,"height":1},"opacity":1,"edgeAntialiasingMask":251658240,"height":569,"hidden":false,"anchorPoint":{"pointX":0.5,"pointY":0.5}},"layers":[{"animations":[],"layers":[],"texturedRectangle":{"singleTextureOpacity":1,"textXHeight":0,"shapePath":{"lineWidth":1,"flatness":0.59999999999999998,"lineCapStyle":0,"elements":[{"type":"MoveToPoint","points":[[6.1320457458496094,8.7251052856445312]]},{"type":"AddLine","points":[[922.47974014282227,8.7251052856445312]]},{"type":"AddLine","points":[[922.47974014282227,560.7251033782959]]},{"type":"AddLine","points":[[6.1320457458496094,560.7251033782959]]},{"type":"CloseSubpath"},{"type":"MoveToPoint","points":[[6.1320457458496094,8.7251052856445312]]}],"windingRule":0,"lineJoinStyle":0,"miterLimit":10},"isBackgroundTexture":true,"textBaseline":0,"isVerticalText":false,"textureType":5},"initialState":{"affineTransform":[1,0,0,1,0,0],"masksToBounds":false,"rotation":0,"scale":1,"position":{"pointX":458.36795425415039,"pointY":275.77489471435547},"width":929,"sublayerTransform":[1,0,0,0,0,1,0,0,0,0,1,0,0,0,0,1],"contentsRect":{"y":0,"x":0,"width":1,"height":1},"opacity":1,"edgeAntialiasingMask":0,"height":569,"hidden":false,"anchorPoint":{"pointX":0.5,"pointY":0.5}},"texture":"34C4F3867BF19FFC7B3A9911BD63353D"}]}]},{"animations":[],"initialState":{"affineTransform":[1,0,0,1,0,0],"masksToBounds":false,"rotation":0,"scale":1,"position":{"pointX":960,"pointY":540},"width":1920,"sublayerTransform":[1,0,0,0,0,1,0,0,0,0,1,0,0,0,0,1],"contentsRect":{"y":0,"x":0,"width":1,"height":1},"opacity":1,"edgeAntialiasingMask":251658240,"height":1080,"hidden":false,"anchorPoint":{"pointX":0.5,"pointY":0.5}},"layers":[{"animations":[],"initialState":{"affineTransform":[1,0,0,1,0,0],"masksToBounds":false,"rotation":0,"scale":1,"position":{"pointX":1438.166259765625,"pointY":306.32223129272461},"width":913,"sublayerTransform":[1,0,0,0,0,1,0,0,0,0,1,0,0,0,0,1],"contentsRect":{"y":0,"x":0,"width":1,"height":1},"opacity":1,"edgeAntialiasingMask":251658240,"height":569,"hidden":false,"anchorPoint":{"pointX":0.5,"pointY":0.5}},"layers":[{"animations":[],"layers":[],"texturedRectangle":{"singleTextureOpacity":1,"textXHeight":0,"shapePath":{"lineWidth":1,"flatness":0.59999999999999998,"lineCapStyle":0,"elements":[{"type":"MoveToPoint","points":[[6.666259765625,8.8222312927246094]]},{"type":"AddLine","points":[[906.21116638183594,8.8222312927246094]]},{"type":"AddLine","points":[[906.21116638183594,560.82222938537598]]},{"type":"AddLine","points":[[6.666259765625,560.82222938537598]]},{"type":"CloseSubpath"},{"type":"MoveToPoint","points":[[6.666259765625,8.8222312927246094]]}],"windingRule":0,"lineJoinStyle":0,"miterLimit":10},"isBackgroundTexture":true,"textBaseline":0,"isVerticalText":false,"textureType":5},"initialState":{"affineTransform":[1,0,0,1,0,0],"masksToBounds":false,"rotation":0,"scale":1,"position":{"pointX":449.833740234375,"pointY":275.67776870727539},"width":913,"sublayerTransform":[1,0,0,0,0,1,0,0,0,0,1,0,0,0,0,1],"contentsRect":{"y":0,"x":0,"width":1,"height":1},"opacity":1,"edgeAntialiasingMask":0,"height":569,"hidden":false,"anchorPoint":{"pointX":0.5,"pointY":0.5}},"texture":"7F2F06C91810C43EB3771BF2188F303E"}]}]},{"animations":[],"initialState":{"affineTransform":[1,0,0,1,0,0],"masksToBounds":false,"rotation":0,"scale":1,"position":{"pointX":960,"pointY":540},"width":1920,"sublayerTransform":[1,0,0,0,0,1,0,0,0,0,1,0,0,0,0,1],"contentsRect":{"y":0,"x":0,"width":1,"height":1},"opacity":1,"edgeAntialiasingMask":251658240,"height":1080,"hidden":false,"anchorPoint":{"pointX":0.5,"pointY":0.5}},"layers":[{"animations":[],"initialState":{"affineTransform":[1,0,0,1,0,0],"masksToBounds":false,"rotation":0,"scale":1,"position":{"pointX":1438.166259765625,"pointY":839.9832763671875},"width":913,"sublayerTransform":[1,0,0,0,0,1,0,0,0,0,1,0,0,0,0,1],"contentsRect":{"y":0,"x":0,"width":1,"height":1},"opacity":1,"edgeAntialiasingMask":251658240,"height":501,"hidden":false,"anchorPoint":{"pointX":0.5,"pointY":0.5}},"layers":[{"animations":[],"layers":[],"texturedRectangle":{"singleTextureOpacity":1,"textXHeight":0,"shapePath":{"lineWidth":1,"flatness":0.59999999999999998,"lineCapStyle":0,"elements":[{"type":"MoveToPoint","points":[[6.666259765625,8.4832763671875]]},{"type":"AddLine","points":[[906.21116638183594,8.4832763671875]]},{"type":"AddLine","points":[[906.21116638183594,492.48329162597656]]},{"type":"AddLine","points":[[6.666259765625,492.48329162597656]]},{"type":"CloseSubpath"},{"type":"MoveToPoint","points":[[6.666259765625,8.4832763671875]]}],"windingRule":0,"lineJoinStyle":0,"miterLimit":10},"isBackgroundTexture":true,"textBaseline":0,"isVerticalText":false,"textureType":5},"initialState":{"affineTransform":[1,0,0,1,0,0],"masksToBounds":false,"rotation":0,"scale":1,"position":{"pointX":449.833740234375,"pointY":242.0167236328125},"width":913,"sublayerTransform":[1,0,0,0,0,1,0,0,0,0,1,0,0,0,0,1],"contentsRect":{"y":0,"x":0,"width":1,"height":1},"opacity":1,"edgeAntialiasingMask":0,"height":501,"hidden":false,"anchorPoint":{"pointX":0.5,"pointY":0.5}},"texture":"7203CA2CE230D6DFACC528958CF7C285"}]}]},{"animations":[],"initialState":{"affineTransform":[1,0,0,1,0,0],"masksToBounds":false,"rotation":0,"scale":1,"position":{"pointX":960,"pointY":540},"width":1920,"sublayerTransform":[1,0,0,0,0,1,0,0,0,0,1,0,0,0,0,1],"contentsRect":{"y":0,"x":0,"width":1,"height":1},"opacity":1,"edgeAntialiasingMask":251658240,"height":1080,"hidden":false,"anchorPoint":{"pointX":0.5,"pointY":0.5}},"layers":[{"animations":[],"initialState":{"affineTransform":[1,0,0,1,0,0],"masksToBounds":false,"rotation":0,"scale":1,"position":{"pointX":523.18983459472656,"pointY":220.03970336914057},"width":632,"sublayerTransform":[1,0,0,0,0,1,0,0,0,0,1,0,0,0,0,1],"contentsRect":{"y":0,"x":0,"width":1,"height":1},"opacity":1,"edgeAntialiasingMask":251658240,"height":50,"hidden":false,"anchorPoint":{"pointX":0.5,"pointY":0.5}},"objectID":"D19386EA-EAAF-409A-8BF1-31A36E6B159C","layers":[{"animations":[],"layers":[],"texturedRectangle":{"singleTextureOpacity":1,"textXHeight":0,"shapePath":{"lineWidth":1,"flatness":0.59999999999999998,"lineCapStyle":0,"elements":[{"type":"MoveToPoint","points":[[3.6898345947265625,3.5397033691405682]]},{"type":"AddLine","points":[[628.26271057128906,3.5397033691405682]]},{"type":"AddLine","points":[[628.26271057128906,46.383338928222656]]},{"type":"AddLine","points":[[3.6898345947265625,46.383338928222656]]},{"type":"CloseSubpath"},{"type":"MoveToPoint","points":[[3.6898345947265625,3.5397033691405682]]}],"windingRule":0,"lineJoinStyle":0,"miterLimit":10},"isBackgroundTexture":true,"textBaseline":0,"isVerticalText":false,"textureType":5},"initialState":{"affineTransform":[1,0,0,1,0,0],"masksToBounds":false,"rotation":0,"scale":1,"position":{"pointX":314.81016540527344,"pointY":23.960296630859432},"width":632,"sublayerTransform":[1,0,0,0,0,1,0,0,0,0,1,0,0,0,0,1],"contentsRect":{"y":0,"x":0,"width":1,"height":1},"opacity":1,"edgeAntialiasingMask":0,"height":50,"hidden":true,"anchorPoint":{"pointX":0.5,"pointY":0.5}},"texture":"B677092A5C2F6FCF6CE7E2A154347C83"}]}]},{"animations":[],"initialState":{"affineTransform":[1,0,0,1,0,0],"masksToBounds":false,"rotation":0,"scale":1,"position":{"pointX":960,"pointY":540},"width":1920,"sublayerTransform":[1,0,0,0,0,1,0,0,0,0,1,0,0,0,0,1],"contentsRect":{"y":0,"x":0,"width":1,"height":1},"opacity":1,"edgeAntialiasingMask":251658240,"height":1080,"hidden":false,"anchorPoint":{"pointX":0.5,"pointY":0.5}},"layers":[{"animations":[],"initialState":{"affineTransform":[1,0,0,1,0,0],"masksToBounds":false,"rotation":0,"scale":1,"position":{"pointX":1501.364013671875,"pointY":387.896728515625},"width":775,"sublayerTransform":[1,0,0,0,0,1,0,0,0,0,1,0,0,0,0,1],"contentsRect":{"y":0,"x":0,"width":1,"height":1},"opacity":1,"edgeAntialiasingMask":251658240,"height":43,"hidden":false,"anchorPoint":{"pointX":0.5,"pointY":0.5}},"objectID":"F09FC021-176A-4E9D-A05F-8FFE6D0EC747","layers":[{"animations":[],"layers":[],"texturedRectangle":{"singleTextureOpacity":1,"textXHeight":0,"shapePath":{"lineWidth":1,"flatness":0.59999999999999998,"lineCapStyle":0,"elements":[{"type":"MoveToPoint","points":[[4.364013671875,3.896728515625]]},{"type":"AddLine","points":[[770.97149658203125,3.896728515625]]},{"type":"AddLine","points":[[770.97149658203125,39.008934020996094]]},{"type":"AddLine","points":[[4.364013671875,39.008934020996094]]},{"type":"CloseSubpath"},{"type":"MoveToPoint","points":[[4.364013671875,3.896728515625]]}],"windingRule":0,"lineJoinStyle":0,"miterLimit":10},"isBackgroundTexture":true,"textBaseline":0,"isVerticalText":false,"textureType":5},"initialState":{"affineTransform":[1,0,0,1,0,0],"masksToBounds":false,"rotation":0,"scale":1,"position":{"pointX":385.635986328125,"pointY":20.103271484375},"width":775,"sublayerTransform":[1,0,0,0,0,1,0,0,0,0,1,0,0,0,0,1],"contentsRect":{"y":0,"x":0,"width":1,"height":1},"opacity":1,"edgeAntialiasingMask":0,"height":43,"hidden":true,"anchorPoint":{"pointX":0.5,"pointY":0.5}},"texture":"968CA7F03E8F1452C105F26D19933736"}]}]},{"animations":[],"initialState":{"affineTransform":[1,0,0,1,0,0],"masksToBounds":false,"rotation":0,"scale":1,"position":{"pointX":960,"pointY":540},"width":1920,"sublayerTransform":[1,0,0,0,0,1,0,0,0,0,1,0,0,0,0,1],"contentsRect":{"y":0,"x":0,"width":1,"height":1},"opacity":1,"edgeAntialiasingMask":251658240,"height":1080,"hidden":false,"anchorPoint":{"pointX":0.5,"pointY":0.5}},"layers":[{"animations":[],"initialState":{"affineTransform":[1,0,0,1,0,0],"masksToBounds":false,"rotation":0,"scale":1,"position":{"pointX":1501.1395263671877,"pointY":887.72705078125},"width":776,"sublayerTransform":[1,0,0,0,0,1,0,0,0,0,1,0,0,0,0,1],"contentsRect":{"y":0,"x":0,"width":1,"height":1},"opacity":1,"edgeAntialiasingMask":251658240,"height":48,"hidden":false,"anchorPoint":{"pointX":0.5,"pointY":0.5}},"objectID":"74D074A9-3385-45AC-807B-F34018A5C1FC","layers":[{"animations":[],"layers":[],"texturedRectangle":{"singleTextureOpacity":1,"textXHeight":0,"shapePath":{"lineWidth":1,"flatness":0.59999999999999998,"lineCapStyle":0,"elements":[{"type":"MoveToPoint","points":[[3.6395263671877274,4.22705078125]]},{"type":"AddLine","points":[[771.7322998046875,4.22705078125]]},{"type":"AddLine","points":[[771.7322998046875,43.730411529541016]]},{"type":"AddLine","points":[[3.6395263671877274,43.730411529541016]]},{"type":"CloseSubpath"},{"type":"MoveToPoint","points":[[3.6395263671877274,4.22705078125]]}],"windingRule":0,"lineJoinStyle":0,"miterLimit":10},"isBackgroundTexture":true,"textBaseline":0,"isVerticalText":false,"textureType":5},"initialState":{"affineTransform":[1,0,0,1,0,0],"masksToBounds":false,"rotation":0,"scale":1,"position":{"pointX":386.86047363281227,"pointY":22.27294921875},"width":776,"sublayerTransform":[1,0,0,0,0,1,0,0,0,0,1,0,0,0,0,1],"contentsRect":{"y":0,"x":0,"width":1,"height":1},"opacity":1,"edgeAntialiasingMask":0,"height":48,"hidden":true,"anchorPoint":{"pointX":0.5,"pointY":0.5}},"texture":"DD72240AB455A2760B6508DF0985BD38"}]}]}]}},{"effects":[{"beginTime":0,"baseLayer":{"animations":[],"initialState":{"affineTransform":[1,0,0,1,0,0],"masksToBounds":false,"rotation":0,"scale":1,"position":{"pointX":523.18983459472656,"pointY":220.03970336914057},"width":632,"sublayerTransform":[1,0,0,0,0,1,0,0,0,0,1,0,0,0,0,1],"contentsRect":{"y":0,"x":0,"width":1,"height":1},"opacity":1,"edgeAntialiasingMask":251658240,"height":50,"hidden":false,"anchorPoint":{"pointX":0.5,"pointY":0.5}},"objectID":"D19386EA-EAAF-409A-8BF1-31A36E6B159C","layers":[{"animations":[],"initialState":{"affineTransform":[1,0,0,1,0,0],"masksToBounds":false,"rotation":0,"scale":1,"position":{"pointX":752.81016540527344,"pointY":344.96029663085943},"width":632,"sublayerTransform":[1,0,0,0,0,1,0,0,0,0,1,-0.00035007912466775983,0,0,0,1],"contentsRect":{"y":0,"x":0,"width":1,"height":1},"opacity":1,"edgeAntialiasingMask":251658240,"height":50,"hidden":false,"anchorPoint":{"pointX":1.191155325008344,"pointY":6.8992059326171891}},"layers":[{"animations":[{"additive":false,"timeOffset":0,"beginTime":1e-100,"repeatCount":0,"fillMode":"both","duration":0.5,"autoreverses":false,"animations":[{"repeatCount":0,"removedOnCompletion":true,"from":{"scalar":1},"timingFunction":"EaseInEaseOut","additive":false,"timeOffset":0,"autoreverses":false,"property":"opacity","fillMode":"both","duration":0.5,"beginTime":0,"to":{"scalar":0}}],"removedOnCompletion":false}],"layers":[],"texturedRectangle":{"singleTextureOpacity":1,"textXHeight":0,"shapePath":{"lineWidth":1,"flatness":0.59999999999999998,"lineCapStyle":0,"elements":[{"type":"MoveToPoint","points":[[3.6898345947265625,3.5397033691405682]]},{"type":"AddLine","points":[[628.26271057128906,3.5397033691405682]]},{"type":"AddLine","points":[[628.26271057128906,46.383338928222656]]},{"type":"AddLine","points":[[3.6898345947265625,46.383338928222656]]},{"type":"CloseSubpath"},{"type":"MoveToPoint","points":[[3.6898345947265625,3.5397033691405682]]}],"windingRule":0,"lineJoinStyle":0,"miterLimit":10},"isBackgroundTexture":true,"textBaseline":0,"isVerticalText":false,"textureType":5},"initialState":{"affineTransform":[1,0,0,1,0,0],"masksToBounds":false,"rotation":0,"scale":1,"position":{"pointX":314.81016540527344,"pointY":23.960296630859432},"width":632,"sublayerTransform":[1,0,0,0,0,1,0,0,0,0,1,0,0,0,0,1],"contentsRect":{"y":0,"x":0,"width":1,"height":1},"opacity":1,"edgeAntialiasingMask":0,"height":50,"hidden":false,"anchorPoint":{"pointX":0.5,"pointY":0.5}},"texture":"B677092A5C2F6FCF6CE7E2A154347C83"}]}]},"effects":[],"duration":0.5,"type":"buildOut","attributes":{"direction":0},"name":"apple:dissolve character","objectID":"D19386EA-EAAF-409A-8BF1-31A36E6B159C"},{"beginTime":0,"baseLayer":{"animations":[],"initialState":{"affineTransform":[1,0,0,1,0,0],"masksToBounds":false,"rotation":0,"scale":1,"position":{"pointX":1501.364013671875,"pointY":387.896728515625},"width":775,"sublayerTransform":[1,0,0,0,0,1,0,0,0,0,1,0,0,0,0,1],"contentsRect":{"y":0,"x":0,"width":1,"height":1},"opacity":1,"edgeAntialiasingMask":251658240,"height":43,"hidden":false,"anchorPoint":{"pointX":0.5,"pointY":0.5}},"objectID":"F09FC021-176A-4E9D-A05F-8FFE6D0EC747","layers":[{"animations":[],"initialState":{"affineTransform":[1,0,0,1,0,0],"masksToBounds":false,"rotation":0,"scale":1,"position":{"pointX":-153.864013671875,"pointY":173.603271484375},"width":775,"sublayerTransform":[1,0,0,0,0,1,0,0,0,0,1,-0.00035007912466775983,0,0,0,1],"contentsRect":{"y":0,"x":0,"width":1,"height":1},"opacity":1,"edgeAntialiasingMask":251658240,"height":43,"hidden":false,"anchorPoint":{"pointX":-0.19853421118951614,"pointY":4.0372853833575579}},"layers":[{"animations":[{"additive":false,"timeOffset":0,"beginTime":1e-100,"repeatCount":0,"fillMode":"both","duration":0.5,"autoreverses":false,"animations":[{"repeatCount":0,"removedOnCompletion":true,"from":{"scalar":0},"timingFunction":"EaseInEaseOut","additive":false,"timeOffset":0,"autoreverses":false,"property":"opacity","fillMode":"both","duration":0.5,"beginTime":0,"to":{"scalar":1}},{"additive":false,"timeOffset":0,"beginTime":0,"from":{"scalar":false},"repeatCount":0,"fillMode":"forwards","duration":0.5,"autoreverses":false,"property":"hidden","to":{"scalar":false},"removedOnCompletion":true}],"removedOnCompletion":false}],"layers":[],"texturedRectangle":{"singleTextureOpacity":1,"textXHeight":0,"shapePath":{"lineWidth":1,"flatness":0.59999999999999998,"lineCapStyle":0,"elements":[{"type":"MoveToPoint","points":[[4.364013671875,3.896728515625]]},{"type":"AddLine","points":[[770.97149658203125,3.896728515625]]},{"type":"AddLine","points":[[770.97149658203125,39.008934020996094]]},{"type":"AddLine","points":[[4.364013671875,39.008934020996094]]},{"type":"CloseSubpath"},{"type":"MoveToPoint","points":[[4.364013671875,3.896728515625]]}],"windingRule":0,"lineJoinStyle":0,"miterLimit":10},"isBackgroundTexture":true,"textBaseline":0,"isVerticalText":false,"textureType":5},"initialState":{"affineTransform":[1,0,0,1,0,0],"masksToBounds":false,"rotation":0,"scale":1,"position":{"pointX":385.635986328125,"pointY":20.103271484375},"width":775,"sublayerTransform":[1,0,0,0,0,1,0,0,0,0,1,0,0,0,0,1],"contentsRect":{"y":0,"x":0,"width":1,"height":1},"opacity":1,"edgeAntialiasingMask":0,"height":43,"hidden":true,"anchorPoint":{"pointX":0.5,"pointY":0.5}},"texture":"968CA7F03E8F1452C105F26D19933736"}]}]},"effects":[],"duration":0.5,"type":"buildIn","attributes":{"direction":0},"name":"apple:dissolve character","objectID":"F09FC021-176A-4E9D-A05F-8FFE6D0EC747"},{"beginTime":0,"baseLayer":{"animations":[],"initialState":{"affineTransform":[1,0,0,1,0,0],"masksToBounds":false,"rotation":0,"scale":1,"position":{"pointX":1501.1395263671877,"pointY":887.72705078125},"width":776,"sublayerTransform":[1,0,0,0,0,1,0,0,0,0,1,0,0,0,0,1],"contentsRect":{"y":0,"x":0,"width":1,"height":1},"opacity":1,"edgeAntialiasingMask":251658240,"height":48,"hidden":false,"anchorPoint":{"pointX":0.5,"pointY":0.5}},"objectID":"74D074A9-3385-45AC-807B-F34018A5C1FC","layers":[{"animations":[],"initialState":{"affineTransform":[1,0,0,1,0,0],"masksToBounds":false,"rotation":0,"scale":1,"position":{"pointX":-153.13952636718773,"pointY":-323.72705078125},"width":776,"sublayerTransform":[1,0,0,0,0,1,0,0,0,0,1,-0.00035007912466775983,0,0,0,1],"contentsRect":{"y":0,"x":0,"width":1,"height":1},"opacity":1,"edgeAntialiasingMask":251658240,"height":48,"hidden":false,"anchorPoint":{"pointX":-0.19734475047318006,"pointY":-6.744313557942708}},"layers":[{"animations":[{"additive":false,"timeOffset":0,"beginTime":1e-100,"repeatCount":0,"fillMode":"both","duration":0.5,"autoreverses":false,"animations":[{"repeatCount":0,"removedOnCompletion":true,"from":{"scalar":0},"timingFunction":"EaseInEaseOut","additive":false,"timeOffset":0,"autoreverses":false,"property":"opacity","fillMode":"both","duration":0.5,"beginTime":0,"to":{"scalar":1}},{"additive":false,"timeOffset":0,"beginTime":0,"from":{"scalar":false},"repeatCount":0,"fillMode":"forwards","duration":0.5,"autoreverses":false,"property":"hidden","to":{"scalar":false},"removedOnCompletion":true}],"removedOnCompletion":false}],"layers":[],"texturedRectangle":{"singleTextureOpacity":1,"textXHeight":0,"shapePath":{"lineWidth":1,"flatness":0.59999999999999998,"lineCapStyle":0,"elements":[{"type":"MoveToPoint","points":[[3.6395263671877274,4.22705078125]]},{"type":"AddLine","points":[[771.7322998046875,4.22705078125]]},{"type":"AddLine","points":[[771.7322998046875,43.730411529541016]]},{"type":"AddLine","points":[[3.6395263671877274,43.730411529541016]]},{"type":"CloseSubpath"},{"type":"MoveToPoint","points":[[3.6395263671877274,4.22705078125]]}],"windingRule":0,"lineJoinStyle":0,"miterLimit":10},"isBackgroundTexture":true,"textBaseline":0,"isVerticalText":false,"textureType":5},"initialState":{"affineTransform":[1,0,0,1,0,0],"masksToBounds":false,"rotation":0,"scale":1,"position":{"pointX":386.86047363281227,"pointY":22.27294921875},"width":776,"sublayerTransform":[1,0,0,0,0,1,0,0,0,0,1,0,0,0,0,1],"contentsRect":{"y":0,"x":0,"width":1,"height":1},"opacity":1,"edgeAntialiasingMask":0,"height":48,"hidden":true,"anchorPoint":{"pointX":0.5,"pointY":0.5}},"texture":"DD72240AB455A2760B6508DF0985BD38"}]}]},"effects":[],"duration":0.5,"type":"buildIn","attributes":{"direction":0},"name":"apple:dissolve character","objectID":"74D074A9-3385-45AC-807B-F34018A5C1FC"}],"automaticPlay":false,"hyperlinks":[],"accessibility":[{"text":"    bool try_push (const T& v)","targetRectangle":{"y":25.822231292724609,"x":985.666259765625,"width":504.08203125,"height":34}},{"text":"    {","targetRectangle":{"y":59.822231292724609,"x":985.666259765625,"width":84.013671875,"height":34}},{"text":"        size_t current_tail = tail.load();","targetRectangle":{"y":93.822231292724609,"x":985.666259765625,"width":705.71484375,"height":34}},{"text":"        size_t current_head = head.load();","targetRectangle":{"y":127.82223129272461,"x":985.666259765625,"width":705.71484375,"height":34}},{"text":"        size_t size = current_tail - current_head;","targetRectangle":{"y":195.82223129272461,"x":985.666259765625,"width":840.13671875,"height":34}},{"text":"        if (size >= (capacity - 1)) \/\/ full","targetRectangle":{"y":263.82223129272461,"x":985.666259765625,"width":722.517578125,"height":34}},{"text":"            return false;","targetRectangle":{"y":297.82223129272461,"x":985.666259765625,"width":420.068359375,"height":34}},{"text":"        size_t index = current_tail & (capacity - 1);","targetRectangle":{"y":365.82223129272461,"x":985.666259765625,"width":890.544921875,"height":34}},{"text":"        data[index] = v;","targetRectangle":{"y":399.82223129272461,"x":985.666259765625,"width":403.265625,"height":34}},{"text":"        tail.store (current_tail + 1);","targetRectangle":{"y":433.82223129272461,"x":985.666259765625,"width":638.50390625,"height":34}},{"text":"        return true;","targetRectangle":{"y":501.82223129272461,"x":985.666259765625,"width":336.0546875,"height":34}},{"text":"    }","targetRectangle":{"y":535.82223129272461,"x":985.666259765625,"width":84.013671875,"height":34}},{"text":"template<typename T>","targetRectangle":{"y":27.725105285644531,"x":50.132045745849609,"width":336.0546875,"height":34}},{"text":"class drow_queue_v2","targetRectangle":{"y":61.725105285644531,"x":50.132045745849609,"width":319.251953125,"height":34}},{"text":"{","targetRectangle":{"y":95.725105285644531,"x":50.132045745849609,"width":16.802734375,"height":34}},{"text":"public:","targetRectangle":{"y":129.72510528564453,"x":50.132045745849609,"width":117.619140625,"height":34}},{"text":"    drow_queue_v2 (size_t capacity_)","targetRectangle":{"y":163.72510528564453,"x":50.132045745849609,"width":604.8984375,"height":34}},{"text":"        : capacity (std::bit_ceil (capacity_))","targetRectangle":{"y":197.72510528564453,"x":50.132045745849609,"width":772.92578125,"height":34}},{"text":"    {}","targetRectangle":{"y":231.72510528564453,"x":50.132045745849609,"width":100.81640625,"height":34}},{"text":"    bool try_push (const T&);","targetRectangle":{"y":299.72510528564453,"x":50.132045745849609,"width":487.279296875,"height":34}},{"text":"    bool try_pop (T&);","targetRectangle":{"y":333.72510528564453,"x":50.132045745849609,"width":369.66015625,"height":34}},{"text":"private:","targetRectangle":{"y":401.72510528564453,"x":50.132045745849609,"width":134.421875,"height":34}},{"text":"    size_t capacity = 0;","targetRectangle":{"y":435.72510528564453,"x":50.132045745849609,"width":403.265625,"height":34}},{"text":"    std::vector<T> data { std::vector<T> (capacity) };","targetRectangle":{"y":469.72510528564453,"x":50.132045745849609,"width":907.34765625,"height":34}},{"text":"    std::atomic<size_t> head { 0 }, tail { 0 };","targetRectangle":{"y":503.72510528564453,"x":50.132045745849609,"width":789.728515625,"height":34}},{"text":"};","targetRectangle":{"y":537.72510528564453,"x":50.132045745849609,"width":33.60546875,"height":34}},{"text":"    bool try_pop (T& v)","targetRectangle":{"y":593.4832763671875,"x":985.666259765625,"width":386.462890625,"height":34}},{"text":"    {","targetRectangle":{"y":627.4832763671875,"x":985.666259765625,"width":84.013671875,"height":34}},{"text":"        size_t current_head = head.load();","targetRectangle":{"y":661.4832763671875,"x":985.666259765625,"width":705.71484375,"height":34}},{"text":"        size_t current_tail = tail.load();","targetRectangle":{"y":695.4832763671875,"x":985.666259765625,"width":705.71484375,"height":34}},{"text":"        if (current_head == current_tail) \/\/ empty","targetRectangle":{"y":763.4832763671875,"x":985.666259765625,"width":840.13671875,"height":34}},{"text":"            return false;","targetRectangle":{"y":797.4832763671875,"x":985.666259765625,"width":420.068359375,"height":34}},{"text":"        size_t index = current_head & (capacity - 1);","targetRectangle":{"y":865.4832763671875,"x":985.666259765625,"width":890.544921875,"height":34}},{"text":"        v = data[index];","targetRectangle":{"y":899.4832763671875,"x":985.666259765625,"width":403.265625,"height":34}},{"text":"        head.store(current_head + 1);","targetRectangle":{"y":933.4832763671875,"x":985.666259765625,"width":621.701171875,"height":34}},{"text":"        return true;","targetRectangle":{"y":1001.4832763671875,"x":985.666259765625,"width":336.0546875,"height":34}},{"text":"    }","targetRectangle":{"y":1035.4832763671875,"x":985.666259765625,"width":84.013671875,"height":34}}],"baseLayer":{"animations":[],"initialState":{"affineTransform":[1,0,0,1,0,0],"masksToBounds":false,"rotation":0,"scale":1,"position":{"pointX":960,"pointY":540},"width":1920,"sublayerTransform":[1,0,0,0,0,1,0,0,0,0,1,0,0,0,0,1],"contentsRect":{"y":0,"x":0,"width":1,"height":1},"opacity":1,"edgeAntialiasingMask":251658240,"height":1080,"hidden":false,"anchorPoint":{"pointX":0.5,"pointY":0.5}},"layers":[{"animations":[],"initialState":{"affineTransform":[1,0,0,1,0,0],"masksToBounds":false,"rotation":0,"scale":1,"position":{"pointX":960,"pointY":540},"width":1920,"sublayerTransform":[1,0,0,0,0,1,0,0,0,0,1,0,0,0,0,1],"contentsRect":{"y":0,"x":0,"width":1,"height":1},"opacity":1,"edgeAntialiasingMask":251658240,"height":1080,"hidden":false,"anchorPoint":{"pointX":0.5,"pointY":0.5}},"layers":[{"animations":[],"initialState":{"affineTransform":[1,0,0,1,0,0],"masksToBounds":false,"rotation":0,"scale":1,"position":{"pointX":960,"pointY":540},"width":1920,"sublayerTransform":[1,0,0,0,0,1,0,0,0,0,1,0,0,0,0,1],"contentsRect":{"y":0,"x":0,"width":1,"height":1},"opacity":1,"edgeAntialiasingMask":251658240,"height":1080,"hidden":false,"anchorPoint":{"pointX":0.5,"pointY":0.5}},"layers":[{"animations":[],"layers":[],"texturedRectangle":{"isBackgroundTexture":true,"singleTextureOpacity":1,"textureType":1,"textBaseline":0,"textXHeight":0,"isVerticalText":false},"initialState":{"affineTransform":[1,0,0,1,0,0],"masksToBounds":false,"rotation":0,"scale":1,"position":{"pointX":960,"pointY":540},"width":1920,"sublayerTransform":[1,0,0,0,0,1,0,0,0,0,1,0,0,0,0,1],"contentsRect":{"y":0,"x":0,"width":1,"height":1},"opacity":1,"edgeAntialiasingMask":0,"height":1080,"hidden":false,"anchorPoint":{"pointX":0.5,"pointY":0.5}},"texture":"F9A0A76BAF2A9879A1DAA8312FE7E552"}]}]},{"animations":[],"initialState":{"affineTransform":[1,0,0,1,0,0],"masksToBounds":false,"rotation":0,"scale":1,"position":{"pointX":960,"pointY":540},"width":1920,"sublayerTransform":[1,0,0,0,0,1,0,0,0,0,1,0,0,0,0,1],"contentsRect":{"y":0,"x":0,"width":1,"height":1},"opacity":1,"edgeAntialiasingMask":251658240,"height":1080,"hidden":false,"anchorPoint":{"pointX":0.5,"pointY":0.5}},"layers":[{"animations":[],"initialState":{"affineTransform":[1,0,0,1,0,0],"masksToBounds":false,"rotation":0,"scale":1,"position":{"pointX":510.63204574584961,"pointY":308.22510528564453},"width":929,"sublayerTransform":[1,0,0,0,0,1,0,0,0,0,1,0,0,0,0,1],"contentsRect":{"y":0,"x":0,"width":1,"height":1},"opacity":1,"edgeAntialiasingMask":251658240,"height":569,"hidden":false,"anchorPoint":{"pointX":0.5,"pointY":0.5}},"layers":[{"animations":[],"layers":[],"texturedRectangle":{"singleTextureOpacity":1,"textXHeight":0,"shapePath":{"lineWidth":1,"flatness":0.59999999999999998,"lineCapStyle":0,"elements":[{"type":"MoveToPoint","points":[[6.1320457458496094,8.7251052856445312]]},{"type":"AddLine","points":[[922.47974014282227,8.7251052856445312]]},{"type":"AddLine","points":[[922.47974014282227,560.7251033782959]]},{"type":"AddLine","points":[[6.1320457458496094,560.7251033782959]]},{"type":"CloseSubpath"},{"type":"MoveToPoint","points":[[6.1320457458496094,8.7251052856445312]]}],"windingRule":0,"lineJoinStyle":0,"miterLimit":10},"isBackgroundTexture":true,"textBaseline":0,"isVerticalText":false,"textureType":5},"initialState":{"affineTransform":[1,0,0,1,0,0],"masksToBounds":false,"rotation":0,"scale":1,"position":{"pointX":458.36795425415039,"pointY":275.77489471435547},"width":929,"sublayerTransform":[1,0,0,0,0,1,0,0,0,0,1,0,0,0,0,1],"contentsRect":{"y":0,"x":0,"width":1,"height":1},"opacity":1,"edgeAntialiasingMask":0,"height":569,"hidden":false,"anchorPoint":{"pointX":0.5,"pointY":0.5}},"texture":"34C4F3867BF19FFC7B3A9911BD63353D"}]}]},{"animations":[],"initialState":{"affineTransform":[1,0,0,1,0,0],"masksToBounds":false,"rotation":0,"scale":1,"position":{"pointX":960,"pointY":540},"width":1920,"sublayerTransform":[1,0,0,0,0,1,0,0,0,0,1,0,0,0,0,1],"contentsRect":{"y":0,"x":0,"width":1,"height":1},"opacity":1,"edgeAntialiasingMask":251658240,"height":1080,"hidden":false,"anchorPoint":{"pointX":0.5,"pointY":0.5}},"layers":[{"animations":[],"initialState":{"affineTransform":[1,0,0,1,0,0],"masksToBounds":false,"rotation":0,"scale":1,"position":{"pointX":1438.166259765625,"pointY":306.32223129272461},"width":913,"sublayerTransform":[1,0,0,0,0,1,0,0,0,0,1,0,0,0,0,1],"contentsRect":{"y":0,"x":0,"width":1,"height":1},"opacity":1,"edgeAntialiasingMask":251658240,"height":569,"hidden":false,"anchorPoint":{"pointX":0.5,"pointY":0.5}},"layers":[{"animations":[],"layers":[],"texturedRectangle":{"singleTextureOpacity":1,"textXHeight":0,"shapePath":{"lineWidth":1,"flatness":0.59999999999999998,"lineCapStyle":0,"elements":[{"type":"MoveToPoint","points":[[6.666259765625,8.8222312927246094]]},{"type":"AddLine","points":[[906.21116638183594,8.8222312927246094]]},{"type":"AddLine","points":[[906.21116638183594,560.82222938537598]]},{"type":"AddLine","points":[[6.666259765625,560.82222938537598]]},{"type":"CloseSubpath"},{"type":"MoveToPoint","points":[[6.666259765625,8.8222312927246094]]}],"windingRule":0,"lineJoinStyle":0,"miterLimit":10},"isBackgroundTexture":true,"textBaseline":0,"isVerticalText":false,"textureType":5},"initialState":{"affineTransform":[1,0,0,1,0,0],"masksToBounds":false,"rotation":0,"scale":1,"position":{"pointX":449.833740234375,"pointY":275.67776870727539},"width":913,"sublayerTransform":[1,0,0,0,0,1,0,0,0,0,1,0,0,0,0,1],"contentsRect":{"y":0,"x":0,"width":1,"height":1},"opacity":1,"edgeAntialiasingMask":0,"height":569,"hidden":false,"anchorPoint":{"pointX":0.5,"pointY":0.5}},"texture":"7F2F06C91810C43EB3771BF2188F303E"}]}]},{"animations":[],"initialState":{"affineTransform":[1,0,0,1,0,0],"masksToBounds":false,"rotation":0,"scale":1,"position":{"pointX":960,"pointY":540},"width":1920,"sublayerTransform":[1,0,0,0,0,1,0,0,0,0,1,0,0,0,0,1],"contentsRect":{"y":0,"x":0,"width":1,"height":1},"opacity":1,"edgeAntialiasingMask":251658240,"height":1080,"hidden":false,"anchorPoint":{"pointX":0.5,"pointY":0.5}},"layers":[{"animations":[],"initialState":{"affineTransform":[1,0,0,1,0,0],"masksToBounds":false,"rotation":0,"scale":1,"position":{"pointX":1438.166259765625,"pointY":839.9832763671875},"width":913,"sublayerTransform":[1,0,0,0,0,1,0,0,0,0,1,0,0,0,0,1],"contentsRect":{"y":0,"x":0,"width":1,"height":1},"opacity":1,"edgeAntialiasingMask":251658240,"height":501,"hidden":false,"anchorPoint":{"pointX":0.5,"pointY":0.5}},"layers":[{"animations":[],"layers":[],"texturedRectangle":{"singleTextureOpacity":1,"textXHeight":0,"shapePath":{"lineWidth":1,"flatness":0.59999999999999998,"lineCapStyle":0,"elements":[{"type":"MoveToPoint","points":[[6.666259765625,8.4832763671875]]},{"type":"AddLine","points":[[906.21116638183594,8.4832763671875]]},{"type":"AddLine","points":[[906.21116638183594,492.48329162597656]]},{"type":"AddLine","points":[[6.666259765625,492.48329162597656]]},{"type":"CloseSubpath"},{"type":"MoveToPoint","points":[[6.666259765625,8.4832763671875]]}],"windingRule":0,"lineJoinStyle":0,"miterLimit":10},"isBackgroundTexture":true,"textBaseline":0,"isVerticalText":false,"textureType":5},"initialState":{"affineTransform":[1,0,0,1,0,0],"masksToBounds":false,"rotation":0,"scale":1,"position":{"pointX":449.833740234375,"pointY":242.0167236328125},"width":913,"sublayerTransform":[1,0,0,0,0,1,0,0,0,0,1,0,0,0,0,1],"contentsRect":{"y":0,"x":0,"width":1,"height":1},"opacity":1,"edgeAntialiasingMask":0,"height":501,"hidden":false,"anchorPoint":{"pointX":0.5,"pointY":0.5}},"texture":"7203CA2CE230D6DFACC528958CF7C285"}]}]},{"animations":[],"initialState":{"affineTransform":[1,0,0,1,0,0],"masksToBounds":false,"rotation":0,"scale":1,"position":{"pointX":960,"pointY":540},"width":1920,"sublayerTransform":[1,0,0,0,0,1,0,0,0,0,1,0,0,0,0,1],"contentsRect":{"y":0,"x":0,"width":1,"height":1},"opacity":1,"edgeAntialiasingMask":251658240,"height":1080,"hidden":false,"anchorPoint":{"pointX":0.5,"pointY":0.5}},"layers":[{"animations":[],"initialState":{"affineTransform":[1,0,0,1,0,0],"masksToBounds":false,"rotation":0,"scale":1,"position":{"pointX":523.18983459472656,"pointY":220.03970336914057},"width":632,"sublayerTransform":[1,0,0,0,0,1,0,0,0,0,1,0,0,0,0,1],"contentsRect":{"y":0,"x":0,"width":1,"height":1},"opacity":1,"edgeAntialiasingMask":251658240,"height":50,"hidden":false,"anchorPoint":{"pointX":0.5,"pointY":0.5}},"objectID":"D19386EA-EAAF-409A-8BF1-31A36E6B159C","layers":[{"animations":[],"layers":[],"texturedRectangle":{"singleTextureOpacity":1,"textXHeight":0,"shapePath":{"lineWidth":1,"flatness":0.59999999999999998,"lineCapStyle":0,"elements":[{"type":"MoveToPoint","points":[[3.6898345947265625,3.5397033691405682]]},{"type":"AddLine","points":[[628.26271057128906,3.5397033691405682]]},{"type":"AddLine","points":[[628.26271057128906,46.383338928222656]]},{"type":"AddLine","points":[[3.6898345947265625,46.383338928222656]]},{"type":"CloseSubpath"},{"type":"MoveToPoint","points":[[3.6898345947265625,3.5397033691405682]]}],"windingRule":0,"lineJoinStyle":0,"miterLimit":10},"isBackgroundTexture":true,"textBaseline":0,"isVerticalText":false,"textureType":5},"initialState":{"affineTransform":[1,0,0,1,0,0],"masksToBounds":false,"rotation":0,"scale":1,"position":{"pointX":314.81016540527344,"pointY":23.960296630859432},"width":632,"sublayerTransform":[1,0,0,0,0,1,0,0,0,0,1,0,0,0,0,1],"contentsRect":{"y":0,"x":0,"width":1,"height":1},"opacity":1,"edgeAntialiasingMask":0,"height":50,"hidden":false,"anchorPoint":{"pointX":0.5,"pointY":0.5}},"texture":"B677092A5C2F6FCF6CE7E2A154347C83"}]}]},{"animations":[],"initialState":{"affineTransform":[1,0,0,1,0,0],"masksToBounds":false,"rotation":0,"scale":1,"position":{"pointX":960,"pointY":540},"width":1920,"sublayerTransform":[1,0,0,0,0,1,0,0,0,0,1,0,0,0,0,1],"contentsRect":{"y":0,"x":0,"width":1,"height":1},"opacity":1,"edgeAntialiasingMask":251658240,"height":1080,"hidden":false,"anchorPoint":{"pointX":0.5,"pointY":0.5}},"layers":[{"animations":[],"initialState":{"affineTransform":[1,0,0,1,0,0],"masksToBounds":false,"rotation":0,"scale":1,"position":{"pointX":1501.364013671875,"pointY":387.896728515625},"width":775,"sublayerTransform":[1,0,0,0,0,1,0,0,0,0,1,0,0,0,0,1],"contentsRect":{"y":0,"x":0,"width":1,"height":1},"opacity":1,"edgeAntialiasingMask":251658240,"height":43,"hidden":false,"anchorPoint":{"pointX":0.5,"pointY":0.5}},"objectID":"F09FC021-176A-4E9D-A05F-8FFE6D0EC747","layers":[{"animations":[],"layers":[],"texturedRectangle":{"singleTextureOpacity":1,"textXHeight":0,"shapePath":{"lineWidth":1,"flatness":0.59999999999999998,"lineCapStyle":0,"elements":[{"type":"MoveToPoint","points":[[4.364013671875,3.896728515625]]},{"type":"AddLine","points":[[770.97149658203125,3.896728515625]]},{"type":"AddLine","points":[[770.97149658203125,39.008934020996094]]},{"type":"AddLine","points":[[4.364013671875,39.008934020996094]]},{"type":"CloseSubpath"},{"type":"MoveToPoint","points":[[4.364013671875,3.896728515625]]}],"windingRule":0,"lineJoinStyle":0,"miterLimit":10},"isBackgroundTexture":true,"textBaseline":0,"isVerticalText":false,"textureType":5},"initialState":{"affineTransform":[1,0,0,1,0,0],"masksToBounds":false,"rotation":0,"scale":1,"position":{"pointX":385.635986328125,"pointY":20.103271484375},"width":775,"sublayerTransform":[1,0,0,0,0,1,0,0,0,0,1,0,0,0,0,1],"contentsRect":{"y":0,"x":0,"width":1,"height":1},"opacity":1,"edgeAntialiasingMask":0,"height":43,"hidden":true,"anchorPoint":{"pointX":0.5,"pointY":0.5}},"texture":"968CA7F03E8F1452C105F26D19933736"}]}]},{"animations":[],"initialState":{"affineTransform":[1,0,0,1,0,0],"masksToBounds":false,"rotation":0,"scale":1,"position":{"pointX":960,"pointY":540},"width":1920,"sublayerTransform":[1,0,0,0,0,1,0,0,0,0,1,0,0,0,0,1],"contentsRect":{"y":0,"x":0,"width":1,"height":1},"opacity":1,"edgeAntialiasingMask":251658240,"height":1080,"hidden":false,"anchorPoint":{"pointX":0.5,"pointY":0.5}},"layers":[{"animations":[],"initialState":{"affineTransform":[1,0,0,1,0,0],"masksToBounds":false,"rotation":0,"scale":1,"position":{"pointX":1501.1395263671877,"pointY":887.72705078125},"width":776,"sublayerTransform":[1,0,0,0,0,1,0,0,0,0,1,0,0,0,0,1],"contentsRect":{"y":0,"x":0,"width":1,"height":1},"opacity":1,"edgeAntialiasingMask":251658240,"height":48,"hidden":false,"anchorPoint":{"pointX":0.5,"pointY":0.5}},"objectID":"74D074A9-3385-45AC-807B-F34018A5C1FC","layers":[{"animations":[],"layers":[],"texturedRectangle":{"singleTextureOpacity":1,"textXHeight":0,"shapePath":{"lineWidth":1,"flatness":0.59999999999999998,"lineCapStyle":0,"elements":[{"type":"MoveToPoint","points":[[3.6395263671877274,4.22705078125]]},{"type":"AddLine","points":[[771.7322998046875,4.22705078125]]},{"type":"AddLine","points":[[771.7322998046875,43.730411529541016]]},{"type":"AddLine","points":[[3.6395263671877274,43.730411529541016]]},{"type":"CloseSubpath"},{"type":"MoveToPoint","points":[[3.6395263671877274,4.22705078125]]}],"windingRule":0,"lineJoinStyle":0,"miterLimit":10},"isBackgroundTexture":true,"textBaseline":0,"isVerticalText":false,"textureType":5},"initialState":{"affineTransform":[1,0,0,1,0,0],"masksToBounds":false,"rotation":0,"scale":1,"position":{"pointX":386.86047363281227,"pointY":22.27294921875},"width":776,"sublayerTransform":[1,0,0,0,0,1,0,0,0,0,1,0,0,0,0,1],"contentsRect":{"y":0,"x":0,"width":1,"height":1},"opacity":1,"edgeAntialiasingMask":0,"height":48,"hidden":true,"anchorPoint":{"pointX":0.5,"pointY":0.5}},"texture":"DD72240AB455A2760B6508DF0985BD38"}]}]}]}},{"effects":[{"beginTime":0,"baseLayer":{"animations":[],"initialState":{"affineTransform":[1,0,0,1,0,0],"masksToBounds":false,"rotation":0,"scale":1,"position":{"pointX":960,"pointY":540},"width":1920,"sublayerTransform":[1,0,0,0,0,1,0,0,0,0,1,0,0,0,0,1],"contentsRect":{"y":0,"x":0,"width":1,"height":1},"opacity":1,"edgeAntialiasingMask":251658240,"height":1080,"hidden":false,"anchorPoint":{"pointX":0.5,"pointY":0.5}},"objectID":"0","layers":[{"animations":[],"initialState":{"affineTransform":[1,0,0,1,0,0],"masksToBounds":false,"rotation":0,"scale":1,"position":{"pointX":960,"pointY":540},"width":1920,"sublayerTransform":[1,0,0,0,0,1,0,0,0,0,1,-0.00035007912466775983,0,0,0,1],"contentsRect":{"y":0,"x":0,"width":1,"height":1},"opacity":1,"edgeAntialiasingMask":251658240,"height":1080,"hidden":false,"anchorPoint":{"pointX":0.5,"pointY":0.5}},"layers":[{"animations":[],"layers":[],"texturedRectangle":{"isBackgroundTexture":false,"singleTextureOpacity":1,"textureType":0,"textBaseline":0,"textXHeight":0,"isVerticalText":false},"initialState":{"affineTransform":[1,0,0,1,0,0],"masksToBounds":false,"rotation":0,"scale":1,"position":{"pointX":960,"pointY":540},"width":1920,"sublayerTransform":[1,0,0,0,0,1,0,0,0,0,1,0,0,0,0,1],"contentsRect":{"y":0,"x":0,"width":1,"height":1},"opacity":1,"edgeAntialiasingMask":0,"height":1080,"hidden":false,"anchorPoint":{"pointX":0.5,"pointY":0.5}},"texture":"E46FF30837A55F9CB3342795BC784F21"},{"animations":[{"additive":false,"timeOffset":0,"beginTime":0,"from":{"scalar":false},"repeatCount":0,"fillMode":"both","duration":0.001,"autoreverses":false,"property":"hidden","to":{"scalar":true},"removedOnCompletion":false}],"layers":[],"texturedRectangle":{"isBackgroundTexture":false,"singleTextureOpacity":1,"textureType":0,"textBaseline":0,"textXHeight":0,"isVerticalText":false},"initialState":{"affineTransform":[1,0,0,1,0,0],"masksToBounds":false,"rotation":0,"scale":1,"position":{"pointX":960,"pointY":540},"width":1920,"sublayerTransform":[1,0,0,0,0,1,0,0,0,0,1,0,0,0,0,1],"contentsRect":{"y":0,"x":0,"width":1,"height":1},"opacity":1,"edgeAntialiasingMask":0,"height":1080,"hidden":false,"anchorPoint":{"pointX":0.5,"pointY":0.5}},"texture":"C6AA0A31C6E0D3FCC48F42F06797D8CF"}]}]},"effects":[],"duration":0.001,"type":"transition","attributes":{"direction":0},"name":"none","objectID":"0"}],"automaticPlay":false,"hyperlinks":[],"accessibility":[{"text":"    bool try_push (const T& v)","targetRectangle":{"y":25.822231292724609,"x":985.666259765625,"width":504.08203125,"height":34}},{"text":"    {","targetRectangle":{"y":59.822231292724609,"x":985.666259765625,"width":84.013671875,"height":34}},{"text":"        size_t current_tail = tail.load();","targetRectangle":{"y":93.822231292724609,"x":985.666259765625,"width":705.71484375,"height":34}},{"text":"        size_t current_head = head.load();","targetRectangle":{"y":127.82223129272461,"x":985.666259765625,"width":705.71484375,"height":34}},{"text":"        size_t size = current_tail - current_head;","targetRectangle":{"y":195.82223129272461,"x":985.666259765625,"width":840.13671875,"height":34}},{"text":"        if (size >= (capacity - 1)) \/\/ full","targetRectangle":{"y":263.82223129272461,"x":985.666259765625,"width":722.517578125,"height":34}},{"text":"            return false;","targetRectangle":{"y":297.82223129272461,"x":985.666259765625,"width":420.068359375,"height":34}},{"text":"        size_t index = current_tail & (capacity - 1);","targetRectangle":{"y":365.82223129272461,"x":985.666259765625,"width":890.544921875,"height":34}},{"text":"        data[index] = v;","targetRectangle":{"y":399.82223129272461,"x":985.666259765625,"width":403.265625,"height":34}},{"text":"        tail.store (current_tail + 1);","targetRectangle":{"y":433.82223129272461,"x":985.666259765625,"width":638.50390625,"height":34}},{"text":"        return true;","targetRectangle":{"y":501.82223129272461,"x":985.666259765625,"width":336.0546875,"height":34}},{"text":"    }","targetRectangle":{"y":535.82223129272461,"x":985.666259765625,"width":84.013671875,"height":34}},{"text":"template<typename T>","targetRectangle":{"y":27.725105285644531,"x":50.132045745849609,"width":336.0546875,"height":34}},{"text":"class drow_queue_v2","targetRectangle":{"y":61.725105285644531,"x":50.132045745849609,"width":319.251953125,"height":34}},{"text":"{","targetRectangle":{"y":95.725105285644531,"x":50.132045745849609,"width":16.802734375,"height":34}},{"text":"public:","targetRectangle":{"y":129.72510528564453,"x":50.132045745849609,"width":117.619140625,"height":34}},{"text":"    drow_queue_v2 (size_t capacity_)","targetRectangle":{"y":163.72510528564453,"x":50.132045745849609,"width":604.8984375,"height":34}},{"text":"        : capacity (std::bit_ceil (capacity_))","targetRectangle":{"y":197.72510528564453,"x":50.132045745849609,"width":772.92578125,"height":34}},{"text":"    {}","targetRectangle":{"y":231.72510528564453,"x":50.132045745849609,"width":100.81640625,"height":34}},{"text":"    bool try_push (const T&);","targetRectangle":{"y":299.72510528564453,"x":50.132045745849609,"width":487.279296875,"height":34}},{"text":"    bool try_pop (T&);","targetRectangle":{"y":333.72510528564453,"x":50.132045745849609,"width":369.66015625,"height":34}},{"text":"private:","targetRectangle":{"y":401.72510528564453,"x":50.132045745849609,"width":134.421875,"height":34}},{"text":"    size_t capacity = 0;","targetRectangle":{"y":435.72510528564453,"x":50.132045745849609,"width":403.265625,"height":34}},{"text":"    std::vector<T> data { std::vector<T> (capacity) };","targetRectangle":{"y":469.72510528564453,"x":50.132045745849609,"width":907.34765625,"height":34}},{"text":"    std::atomic<size_t> head { 0 }, tail { 0 };","targetRectangle":{"y":503.72510528564453,"x":50.132045745849609,"width":789.728515625,"height":34}},{"text":"};","targetRectangle":{"y":537.72510528564453,"x":50.132045745849609,"width":33.60546875,"height":34}},{"text":"    bool try_pop (T& v)","targetRectangle":{"y":593.4832763671875,"x":985.666259765625,"width":386.462890625,"height":34}},{"text":"    {","targetRectangle":{"y":627.4832763671875,"x":985.666259765625,"width":84.013671875,"height":34}},{"text":"        size_t current_head = head.load();","targetRectangle":{"y":661.4832763671875,"x":985.666259765625,"width":705.71484375,"height":34}},{"text":"        size_t current_tail = tail.load();","targetRectangle":{"y":695.4832763671875,"x":985.666259765625,"width":705.71484375,"height":34}},{"text":"        if (current_head == current_tail) \/\/ empty","targetRectangle":{"y":763.4832763671875,"x":985.666259765625,"width":840.13671875,"height":34}},{"text":"            return false;","targetRectangle":{"y":797.4832763671875,"x":985.666259765625,"width":420.068359375,"height":34}},{"text":"        size_t index = current_head & (capacity - 1);","targetRectangle":{"y":865.4832763671875,"x":985.666259765625,"width":890.544921875,"height":34}},{"text":"        v = data[index];","targetRectangle":{"y":899.4832763671875,"x":985.666259765625,"width":403.265625,"height":34}},{"text":"        head.store(current_head + 1);","targetRectangle":{"y":933.4832763671875,"x":985.666259765625,"width":621.701171875,"height":34}},{"text":"        return true;","targetRectangle":{"y":1001.4832763671875,"x":985.666259765625,"width":336.0546875,"height":34}},{"text":"    }","targetRectangle":{"y":1035.4832763671875,"x":985.666259765625,"width":84.013671875,"height":34}}],"baseLayer":{"animations":[],"initialState":{"affineTransform":[1,0,0,1,0,0],"masksToBounds":false,"rotation":0,"scale":1,"position":{"pointX":960,"pointY":540},"width":1920,"sublayerTransform":[1,0,0,0,0,1,0,0,0,0,1,0,0,0,0,1],"contentsRect":{"y":0,"x":0,"width":1,"height":1},"opacity":1,"edgeAntialiasingMask":251658240,"height":1080,"hidden":false,"anchorPoint":{"pointX":0.5,"pointY":0.5}},"objectID":"0","layers":[{"animations":[],"initialState":{"affineTransform":[1,0,0,1,0,0],"masksToBounds":false,"rotation":0,"scale":1,"position":{"pointX":960,"pointY":540},"width":1920,"sublayerTransform":[1,0,0,0,0,1,0,0,0,0,1,-0.00035007912466775983,0,0,0,1],"contentsRect":{"y":0,"x":0,"width":1,"height":1},"opacity":1,"edgeAntialiasingMask":251658240,"height":1080,"hidden":false,"anchorPoint":{"pointX":0.5,"pointY":0.5}},"layers":[{"animations":[],"layers":[],"texturedRectangle":{"isBackgroundTexture":false,"singleTextureOpacity":1,"textureType":0,"textBaseline":0,"textXHeight":0,"isVerticalText":false},"initialState":{"affineTransform":[1,0,0,1,0,0],"masksToBounds":false,"rotation":0,"scale":1,"position":{"pointX":960,"pointY":540},"width":1920,"sublayerTransform":[1,0,0,0,0,1,0,0,0,0,1,0,0,0,0,1],"contentsRect":{"y":0,"x":0,"width":1,"height":1},"opacity":1,"edgeAntialiasingMask":0,"height":1080,"hidden":false,"anchorPoint":{"pointX":0.5,"pointY":0.5}},"texture":"C6AA0A31C6E0D3FCC48F42F06797D8CF"}]}]}}]}