{"assets":{"F9A0A76BAF2A9879A1DAA8312FE7E552":{"type":"texture","index":0,"url":{"native":"assets\/C8D63AB0-9537-4AFF-95DD-FF7FFE7DFD95.pdf"},"width":1920,"height":1080},"07B1EF5E7DBD0FE096EBCD5BF0CB747D":{"type":"texture","index":3,"url":{"native":"assets\/C8D63AB0-9537-4AFF-95DD-FF7FFE7DFD95.pdf"},"width":738,"height":36},"103FD9B870C485FA2C10AF83D6AA848C":{"type":"texture","index":7,"url":{"native":"assets\/C8D63AB0-9537-4AFF-95DD-FF7FFE7DFD95.pdf"},"width":1920,"height":1080},"6882CA34338C7DA31EE83EDB94DF20A6":{"type":"texture","index":4,"url":{"native":"assets\/C8D63AB0-9537-4AFF-95DD-FF7FFE7DFD95.pdf"},"width":958,"height":43},"3E7AC91706FC8DE5080498FF81185346":{"type":"texture","index":6,"url":{"native":"assets\/C8D63AB0-9537-4AFF-95DD-FF7FFE7DFD95.pdf"},"width":1920,"height":1080},"4E38E8EE8C81539C7C6B3F9891BFC9DE":{"type":"texture","index":5,"url":{"native":"assets\/C8D63AB0-9537-4AFF-95DD-FF7FFE7DFD95.pdf"},"width":25,"height":19},"45FF1384BB6254CC61065789E45DDE73":{"type":"texture","index":1,"url":{"native":"assets\/C8D63AB0-9537-4AFF-95DD-FF7FFE7DFD95.pdf"},"width":331,"height":126},"E1F6DBBADD9269EB94F2D6EDBB407B29":{"type":"texture","index":2,"url":{"native":"assets\/C8D63AB0-9537-4AFF-95DD-FF7FFE7DFD95.pdf"},"width":555,"height":43}},"events":[{"effects":[{"beginTime":0,"baseLayer":{"animations":[],"initialState":{"affineTransform":[1,0,0,1,0,0],"masksToBounds":false,"rotation":0,"scale":1,"position":{"pointX":592,"pointY":330.82199096679688},"width":994,"sublayerTransform":[1,0,0,0,0,1,0,0,0,0,1,0,0,0,0,1],"contentsRect":{"y":0,"x":0,"width":1,"height":1},"opacity":1,"edgeAntialiasingMask":251658240,"height":245,"hidden":false,"anchorPoint":{"pointX":0.5,"pointY":0.5}},"objectID":"7F028A4D-19D9-46BE-BBE2-3960A1D547CF","layers":[{"animations":[],"initialState":{"affineTransform":[1,0,0,1,0,0],"masksToBounds":false,"rotation":0,"scale":1,"position":{"pointX":865,"pointY":331.67800903320312},"width":994,"sublayerTransform":[1,0,0,0,0,1,0,0,0,0,1,-0.00035007912466775983,0,0,0,1],"contentsRect":{"y":0,"x":0,"width":1,"height":1},"opacity":1,"edgeAntialiasingMask":251658240,"height":245,"hidden":false,"anchorPoint":{"pointX":0.87022132796780682,"pointY":1.3537877919722576}},"layers":[{"animations":[{"additive":false,"timeOffset":0,"beginTime":1e-100,"repeatCount":0,"fillMode":"both","duration":0.001,"autoreverses":false,"animations":[{"additive":false,"timeOffset":0,"beginTime":0,"from":{"scalar":true},"repeatCount":0,"fillMode":"both","duration":0.0001,"autoreverses":false,"property":"hidden","to":{"scalar":false},"removedOnCompletion":true},{"additive":false,"timeOffset":0,"beginTime":0.0001,"from":{"scalar":false},"repeatCount":0,"fillMode":"forwards","duration":0.00089999999999999998,"autoreverses":false,"property":"hidden","to":{"scalar":false},"removedOnCompletion":true}],"removedOnCompletion":false}],"layers":[],"texturedRectangle":{"singleTextureOpacity":1,"textXHeight":0.48651162790697677,"textBaseline":0.7702784261038137,"isBackgroundTexture":false,"isVerticalText":false,"textColor":[0.32481390237808228,0.34466239809989929,0.37378150224685669,1],"textureType":6},"initialState":{"affineTransform":[1,0,0,1,0,0],"masksToBounds":false,"rotation":0,"scale":1,"position":{"pointX":283.5,"pointY":36.178009033203125},"width":555,"sublayerTransform":[1,0,0,0,0,1,0,0,0,0,1,0,0,0,0,1],"contentsRect":{"y":0,"x":0,"width":1,"height":1},"opacity":1,"edgeAntialiasingMask":0,"height":43,"hidden":true,"anchorPoint":{"pointX":0.5,"pointY":0.5}},"texture":"E1F6DBBADD9269EB94F2D6EDBB407B29"}]},{"animations":[],"layers":[],"texturedRectangle":{"singleTextureOpacity":1,"textXHeight":0.58111111111111113,"textBaseline":0.92005478673511076,"isBackgroundTexture":false,"isVerticalText":false,"textColor":[0.32481390237808228,0.34466239809989929,0.37378150224685669,1],"textureType":6},"initialState":{"affineTransform":[1,0,0,1,0,0],"masksToBounds":false,"rotation":0,"scale":1,"position":{"pointX":375,"pointY":133.67800903320312},"width":738,"sublayerTransform":[1,0,0,0,0,1,0,0,0,0,1,0,0,0,0,1],"contentsRect":{"y":0,"x":0,"width":1,"height":1},"opacity":1,"edgeAntialiasingMask":0,"height":36,"hidden":true,"anchorPoint":{"pointX":0.5,"pointY":0.5}},"texture":"07B1EF5E7DBD0FE096EBCD5BF0CB747D"},{"animations":[],"layers":[],"texturedRectangle":{"singleTextureOpacity":1,"textXHeight":0.48651162790697677,"textBaseline":0.7702784261038137,"isBackgroundTexture":false,"isVerticalText":false,"textColor":[0.32481390237808228,0.34466239809989929,0.37378150224685669,1],"textureType":6},"initialState":{"affineTransform":[1,0,0,1,0,0],"masksToBounds":false,"rotation":0,"scale":1,"position":{"pointX":521,"pointY":238.17800903320312},"width":958,"sublayerTransform":[1,0,0,0,0,1,0,0,0,0,1,0,0,0,0,1],"contentsRect":{"y":0,"x":0,"width":1,"height":1},"opacity":1,"edgeAntialiasingMask":0,"height":43,"hidden":true,"anchorPoint":{"pointX":0.5,"pointY":0.5}},"texture":"6882CA34338C7DA31EE83EDB94DF20A6"}]},"effects":[],"duration":0.001,"type":"buildIn","attributes":{"direction":0},"name":"apple:bc-appear","objectID":"7F028A4D-19D9-46BE-BBE2-3960A1D547CF"}],"automaticPlay":false,"hyperlinks":[],"accessibility":[{"text":"￼","targetRectangle":{"y":984.99998712539673,"x":1859.5199754046334,"width":22.079999999999927,"height":25.799999594688416}},{"text":"￼ Tests","targetRectangle":{"y":54,"x":99,"width":333.22888560421768,"height":124.04999807476997}},{"text":"pasted-movie.png","targetRectangle":{"y":55.249951869249344,"x":99,"width":88.888885498046875,"height":100}}],"baseLayer":{"animations":[],"initialState":{"affineTransform":[1,0,0,1,0,0],"masksToBounds":false,"rotation":0,"scale":1,"position":{"pointX":960,"pointY":540},"width":1920,"sublayerTransform":[1,0,0,0,0,1,0,0,0,0,1,0,0,0,0,1],"contentsRect":{"y":0,"x":0,"width":1,"height":1},"opacity":1,"edgeAntialiasingMask":251658240,"height":1080,"hidden":false,"anchorPoint":{"pointX":0.5,"pointY":0.5}},"layers":[{"animations":[],"initialState":{"affineTransform":[1,0,0,1,0,0],"masksToBounds":false,"rotation":0,"scale":1,"position":{"pointX":960,"pointY":540},"width":1920,"sublayerTransform":[1,0,0,0,0,1,0,0,0,0,1,0,0,0,0,1],"contentsRect":{"y":0,"x":0,"width":1,"height":1},"opacity":1,"edgeAntialiasingMask":251658240,"height":1080,"hidden":false,"anchorPoint":{"pointX":0.5,"pointY":0.5}},"layers":[{"animations":[],"initialState":{"affineTransform":[1,0,0,1,0,0],"masksToBounds":false,"rotation":0,"scale":1,"position":{"pointX":960,"pointY":540},"width":1920,"sublayerTransform":[1,0,0,0,0,1,0,0,0,0,1,0,0,0,0,1],"contentsRect":{"y":0,"x":0,"width":1,"height":1},"opacity":1,"edgeAntialiasingMask":251658240,"height":1080,"hidden":false,"anchorPoint":{"pointX":0.5,"pointY":0.5}},"layers":[{"animations":[],"layers":[],"texturedRectangle":{"isBackgroundTexture":true,"singleTextureOpacity":1,"textureType":1,"textBaseline":0,"textXHeight":0,"isVerticalText":false},"initialState":{"affineTransform":[1,0,0,1,0,0],"masksToBounds":false,"rotation":0,"scale":1,"position":{"pointX":960,"pointY":540},"width":1920,"sublayerTransform":[1,0,0,0,0,1,0,0,0,0,1,0,0,0,0,1],"contentsRect":{"y":0,"x":0,"width":1,"height":1},"opacity":1,"edgeAntialiasingMask":0,"height":1080,"hidden":false,"anchorPoint":{"pointX":0.5,"pointY":0.5}},"texture":"F9A0A76BAF2A9879A1DAA8312FE7E552"}]}]},{"animations":[],"initialState":{"affineTransform":[1,0,0,1,0,0],"masksToBounds":false,"rotation":0,"scale":1,"position":{"pointX":960,"pointY":540},"width":1920,"sublayerTransform":[1,0,0,0,0,1,0,0,0,0,1,0,0,0,0,1],"contentsRect":{"y":0,"x":0,"width":1,"height":1},"opacity":1,"edgeAntialiasingMask":251658240,"height":1080,"hidden":false,"anchorPoint":{"pointX":0.5,"pointY":0.5}},"layers":[{"animations":[],"initialState":{"affineTransform":[1,0,0,1,0,0],"masksToBounds":false,"rotation":0,"scale":1,"position":{"pointX":260.50000000000006,"pointY":113.00000000000006},"width":331,"sublayerTransform":[1,0,0,0,0,1,0,0,0,0,1,0,0,0,0,1],"contentsRect":{"y":0,"x":0,"width":1,"height":1},"opacity":1,"edgeAntialiasingMask":251658240,"height":126,"hidden":false,"anchorPoint":{"pointX":0.5,"pointY":0.5}},"layers":[{"animations":[],"layers":[],"texturedRectangle":{"singleTextureOpacity":1,"textXHeight":0.39432539682539686,"textBaseline":0.80357104658134404,"isBackgroundTexture":true,"isVerticalText":false,"textColor":[0.32481390237808228,0.34466239809989929,0.37378150224685669,1],"textureType":6},"initialState":{"affineTransform":[1,0,0,1,0,0],"masksToBounds":false,"rotation":0,"scale":1,"position":{"pointX":168.49999999999994,"pointY":66.999999999999943},"width":331,"sublayerTransform":[1,0,0,0,0,1,0,0,0,0,1,0,0,0,0,1],"contentsRect":{"y":0,"x":0,"width":1,"height":1},"opacity":1,"edgeAntialiasingMask":0,"height":126,"hidden":false,"anchorPoint":{"pointX":0.5,"pointY":0.5}},"texture":"45FF1384BB6254CC61065789E45DDE73"}]}]},{"animations":[],"initialState":{"affineTransform":[1,0,0,1,0,0],"masksToBounds":false,"rotation":0,"scale":1,"position":{"pointX":960,"pointY":540},"width":1920,"sublayerTransform":[1,0,0,0,0,1,0,0,0,0,1,0,0,0,0,1],"contentsRect":{"y":0,"x":0,"width":1,"height":1},"opacity":1,"edgeAntialiasingMask":251658240,"height":1080,"hidden":false,"anchorPoint":{"pointX":0.5,"pointY":0.5}},"layers":[{"animations":[],"initialState":{"affineTransform":[1,0,0,1,0,0],"masksToBounds":false,"rotation":0,"scale":1,"position":{"pointX":592,"pointY":330.82199096679688},"width":994,"sublayerTransform":[1,0,0,0,0,1,0,0,0,0,1,0,0,0,0,1],"contentsRect":{"y":0,"x":0,"width":1,"height":1},"opacity":1,"edgeAntialiasingMask":251658240,"height":245,"hidden":false,"anchorPoint":{"pointX":0.5,"pointY":0.5}},"objectID":"7F028A4D-19D9-46BE-BBE2-3960A1D547CF","layers":[{"animations":[],"layers":[],"texturedRectangle":{"singleTextureOpacity":1,"textXHeight":0.48651162790697677,"textBaseline":0.7702784261038137,"isBackgroundTexture":false,"isVerticalText":false,"textColor":[0.32481390237808228,0.34466239809989929,0.37378150224685669,1],"textureType":6},"initialState":{"affineTransform":[1,0,0,1,0,0],"masksToBounds":false,"rotation":0,"scale":1,"position":{"pointX":283.5,"pointY":36.178009033203125},"width":555,"sublayerTransform":[1,0,0,0,0,1,0,0,0,0,1,0,0,0,0,1],"contentsRect":{"y":0,"x":0,"width":1,"height":1},"opacity":1,"edgeAntialiasingMask":0,"height":43,"hidden":true,"anchorPoint":{"pointX":0.5,"pointY":0.5}},"texture":"E1F6DBBADD9269EB94F2D6EDBB407B29"},{"animations":[],"layers":[],"texturedRectangle":{"singleTextureOpacity":1,"textXHeight":0.58111111111111113,"textBaseline":0.92005478673511076,"isBackgroundTexture":false,"isVerticalText":false,"textColor":[0.32481390237808228,0.34466239809989929,0.37378150224685669,1],"textureType":6},"initialState":{"affineTransform":[1,0,0,1,0,0],"masksToBounds":false,"rotation":0,"scale":1,"position":{"pointX":375,"pointY":133.67800903320312},"width":738,"sublayerTransform":[1,0,0,0,0,1,0,0,0,0,1,0,0,0,0,1],"contentsRect":{"y":0,"x":0,"width":1,"height":1},"opacity":1,"edgeAntialiasingMask":0,"height":36,"hidden":true,"anchorPoint":{"pointX":0.5,"pointY":0.5}},"texture":"07B1EF5E7DBD0FE096EBCD5BF0CB747D"},{"animations":[],"layers":[],"texturedRectangle":{"singleTextureOpacity":1,"textXHeight":0.48651162790697677,"textBaseline":0.7702784261038137,"isBackgroundTexture":false,"isVerticalText":false,"textColor":[0.32481390237808228,0.34466239809989929,0.37378150224685669,1],"textureType":6},"initialState":{"affineTransform":[1,0,0,1,0,0],"masksToBounds":false,"rotation":0,"scale":1,"position":{"pointX":521,"pointY":238.17800903320312},"width":958,"sublayerTransform":[1,0,0,0,0,1,0,0,0,0,1,0,0,0,0,1],"contentsRect":{"y":0,"x":0,"width":1,"height":1},"opacity":1,"edgeAntialiasingMask":0,"height":43,"hidden":true,"anchorPoint":{"pointX":0.5,"pointY":0.5}},"texture":"6882CA34338C7DA31EE83EDB94DF20A6"}]}]},{"animations":[],"initialState":{"affineTransform":[1,0,0,1,0,0],"masksToBounds":false,"rotation":0,"scale":1,"position":{"pointX":960,"pointY":540},"width":1920,"sublayerTransform":[1,0,0,0,0,1,0,0,0,0,1,0,0,0,0,1],"contentsRect":{"y":0,"x":0,"width":1,"height":1},"opacity":1,"edgeAntialiasingMask":251658240,"height":1080,"hidden":false,"anchorPoint":{"pointX":0.5,"pointY":0.5}},"layers":[{"animations":[],"initialState":{"affineTransform":[1,0,0,1,0,0],"masksToBounds":false,"rotation":0,"scale":1,"position":{"pointX":1867.0199754046334,"pointY":990.49998712539673},"width":25,"sublayerTransform":[1,0,0,0,0,1,0,0,0,0,1,0,0,0,0,1],"contentsRect":{"y":0,"x":0,"width":1,"height":1},"opacity":1,"edgeAntialiasingMask":251658240,"height":19,"hidden":false,"anchorPoint":{"pointX":0.5,"pointY":0.5}},"layers":[{"animations":[],"layers":[],"texturedRectangle":{"singleTextureOpacity":1,"textXHeight":0.55052631578947375,"textBaseline":0.91578830543317291,"isBackgroundTexture":true,"isVerticalText":false,"textColor":[0.32481390237808228,0.34466239809989929,0.37378150224685669,1],"textureType":6},"initialState":{"affineTransform":[1,0,0,1,0,0],"masksToBounds":false,"rotation":0,"scale":1,"position":{"pointX":15.980024595366558,"pointY":17.500012874603271},"width":25,"sublayerTransform":[1,0,0,0,0,1,0,0,0,0,1,0,0,0,0,1],"contentsRect":{"y":0,"x":0,"width":1,"height":1},"opacity":1,"edgeAntialiasingMask":0,"height":19,"hidden":false,"anchorPoint":{"pointX":0.5,"pointY":0.5}},"texture":"4E38E8EE8C81539C7C6B3F9891BFC9DE"}]}]}]}},{"effects":[{"beginTime":0,"baseLayer":{"animations":[],"initialState":{"affineTransform":[1,0,0,1,0,0],"masksToBounds":false,"rotation":0,"scale":1,"position":{"pointX":592,"pointY":330.82199096679688},"width":994,"sublayerTransform":[1,0,0,0,0,1,0,0,0,0,1,0,0,0,0,1],"contentsRect":{"y":0,"x":0,"width":1,"height":1},"opacity":1,"edgeAntialiasingMask":251658240,"height":245,"hidden":false,"anchorPoint":{"pointX":0.5,"pointY":0.5}},"objectID":"7F028A4D-19D9-46BE-BBE2-3960A1D547CF","layers":[{"animations":[],"layers":[],"texturedRectangle":{"singleTextureOpacity":1,"textXHeight":0.48651162790697677,"textBaseline":0.7702784261038137,"isBackgroundTexture":false,"isVerticalText":false,"textColor":[0.32481390237808228,0.34466239809989929,0.37378150224685669,1],"textureType":6},"initialState":{"affineTransform":[1,0,0,1,0,0],"masksToBounds":false,"rotation":0,"scale":1,"position":{"pointX":283.5,"pointY":36.178009033203125},"width":555,"sublayerTransform":[1,0,0,0,0,1,0,0,0,0,1,0,0,0,0,1],"contentsRect":{"y":0,"x":0,"width":1,"height":1},"opacity":1,"edgeAntialiasingMask":0,"height":43,"hidden":false,"anchorPoint":{"pointX":0.5,"pointY":0.5}},"texture":"E1F6DBBADD9269EB94F2D6EDBB407B29"},{"animations":[],"initialState":{"affineTransform":[1,0,0,1,0,0],"masksToBounds":false,"rotation":0,"scale":1,"position":{"pointX":865,"pointY":331.67800903320312},"width":994,"sublayerTransform":[1,0,0,0,0,1,0,0,0,0,1,-0.00035007912466775983,0,0,0,1],"contentsRect":{"y":0,"x":0,"width":1,"height":1},"opacity":1,"edgeAntialiasingMask":251658240,"height":245,"hidden":false,"anchorPoint":{"pointX":0.87022132796780682,"pointY":1.3537877919722576}},"layers":[{"animations":[{"additive":false,"timeOffset":0,"beginTime":1e-100,"repeatCount":0,"fillMode":"both","duration":0.001,"autoreverses":false,"animations":[{"additive":false,"timeOffset":0,"beginTime":0,"from":{"scalar":true},"repeatCount":0,"fillMode":"both","duration":0.0001,"autoreverses":false,"property":"hidden","to":{"scalar":false},"removedOnCompletion":true},{"additive":false,"timeOffset":0,"beginTime":0.0001,"from":{"scalar":false},"repeatCount":0,"fillMode":"forwards","duration":0.00089999999999999998,"autoreverses":false,"property":"hidden","to":{"scalar":false},"removedOnCompletion":true}],"removedOnCompletion":false}],"layers":[],"texturedRectangle":{"singleTextureOpacity":1,"textXHeight":0.58111111111111113,"textBaseline":0.92005478673511076,"isBackgroundTexture":false,"isVerticalText":false,"textColor":[0.32481390237808228,0.34466239809989929,0.37378150224685669,1],"textureType":6},"initialState":{"affineTransform":[1,0,0,1,0,0],"masksToBounds":false,"rotation":0,"scale":1,"position":{"pointX":375,"pointY":133.67800903320312},"width":738,"sublayerTransform":[1,0,0,0,0,1,0,0,0,0,1,0,0,0,0,1],"contentsRect":{"y":0,"x":0,"width":1,"height":1},"opacity":1,"edgeAntialiasingMask":0,"height":36,"hidden":true,"anchorPoint":{"pointX":0.5,"pointY":0.5}},"texture":"07B1EF5E7DBD0FE096EBCD5BF0CB747D"}]},{"animations":[],"layers":[],"texturedRectangle":{"singleTextureOpacity":1,"textXHeight":0.48651162790697677,"textBaseline":0.7702784261038137,"isBackgroundTexture":false,"isVerticalText":false,"textColor":[0.32481390237808228,0.34466239809989929,0.37378150224685669,1],"textureType":6},"initialState":{"affineTransform":[1,0,0,1,0,0],"masksToBounds":false,"rotation":0,"scale":1,"position":{"pointX":521,"pointY":238.17800903320312},"width":958,"sublayerTransform":[1,0,0,0,0,1,0,0,0,0,1,0,0,0,0,1],"contentsRect":{"y":0,"x":0,"width":1,"height":1},"opacity":1,"edgeAntialiasingMask":0,"height":43,"hidden":true,"anchorPoint":{"pointX":0.5,"pointY":0.5}},"texture":"6882CA34338C7DA31EE83EDB94DF20A6"}]},"effects":[],"duration":0.001,"type":"buildIn","attributes":{"direction":0},"name":"apple:bc-appear","objectID":"7F028A4D-19D9-46BE-BBE2-3960A1D547CF"}],"automaticPlay":false,"hyperlinks":[],"accessibility":[{"text":"Requires good test coverage","targetRectangle":{"y":212.32199096679688,"x":134.99999904632568,"width":521.36000000000001,"height":52.599999189376831}},{"text":"￼","targetRectangle":{"y":984.99998712539673,"x":1859.5199754046334,"width":22.079999999999927,"height":25.799999594688416}},{"text":"￼ Tests","targetRectangle":{"y":54,"x":99,"width":333.22888560421768,"height":124.04999807476997}},{"text":"pasted-movie.png","targetRectangle":{"y":55.249951869249344,"x":99,"width":88.888885498046875,"height":100}}],"baseLayer":{"animations":[],"initialState":{"affineTransform":[1,0,0,1,0,0],"masksToBounds":false,"rotation":0,"scale":1,"position":{"pointX":960,"pointY":540},"width":1920,"sublayerTransform":[1,0,0,0,0,1,0,0,0,0,1,0,0,0,0,1],"contentsRect":{"y":0,"x":0,"width":1,"height":1},"opacity":1,"edgeAntialiasingMask":251658240,"height":1080,"hidden":false,"anchorPoint":{"pointX":0.5,"pointY":0.5}},"layers":[{"animations":[],"initialState":{"affineTransform":[1,0,0,1,0,0],"masksToBounds":false,"rotation":0,"scale":1,"position":{"pointX":960,"pointY":540},"width":1920,"sublayerTransform":[1,0,0,0,0,1,0,0,0,0,1,0,0,0,0,1],"contentsRect":{"y":0,"x":0,"width":1,"height":1},"opacity":1,"edgeAntialiasingMask":251658240,"height":1080,"hidden":false,"anchorPoint":{"pointX":0.5,"pointY":0.5}},"layers":[{"animations":[],"initialState":{"affineTransform":[1,0,0,1,0,0],"masksToBounds":false,"rotation":0,"scale":1,"position":{"pointX":960,"pointY":540},"width":1920,"sublayerTransform":[1,0,0,0,0,1,0,0,0,0,1,0,0,0,0,1],"contentsRect":{"y":0,"x":0,"width":1,"height":1},"opacity":1,"edgeAntialiasingMask":251658240,"height":1080,"hidden":false,"anchorPoint":{"pointX":0.5,"pointY":0.5}},"layers":[{"animations":[],"layers":[],"texturedRectangle":{"isBackgroundTexture":true,"singleTextureOpacity":1,"textureType":1,"textBaseline":0,"textXHeight":0,"isVerticalText":false},"initialState":{"affineTransform":[1,0,0,1,0,0],"masksToBounds":false,"rotation":0,"scale":1,"position":{"pointX":960,"pointY":540},"width":1920,"sublayerTransform":[1,0,0,0,0,1,0,0,0,0,1,0,0,0,0,1],"contentsRect":{"y":0,"x":0,"width":1,"height":1},"opacity":1,"edgeAntialiasingMask":0,"height":1080,"hidden":false,"anchorPoint":{"pointX":0.5,"pointY":0.5}},"texture":"F9A0A76BAF2A9879A1DAA8312FE7E552"}]}]},{"animations":[],"initialState":{"affineTransform":[1,0,0,1,0,0],"masksToBounds":false,"rotation":0,"scale":1,"position":{"pointX":960,"pointY":540},"width":1920,"sublayerTransform":[1,0,0,0,0,1,0,0,0,0,1,0,0,0,0,1],"contentsRect":{"y":0,"x":0,"width":1,"height":1},"opacity":1,"edgeAntialiasingMask":251658240,"height":1080,"hidden":false,"anchorPoint":{"pointX":0.5,"pointY":0.5}},"layers":[{"animations":[],"initialState":{"affineTransform":[1,0,0,1,0,0],"masksToBounds":false,"rotation":0,"scale":1,"position":{"pointX":260.50000000000006,"pointY":113.00000000000006},"width":331,"sublayerTransform":[1,0,0,0,0,1,0,0,0,0,1,0,0,0,0,1],"contentsRect":{"y":0,"x":0,"width":1,"height":1},"opacity":1,"edgeAntialiasingMask":251658240,"height":126,"hidden":false,"anchorPoint":{"pointX":0.5,"pointY":0.5}},"layers":[{"animations":[],"layers":[],"texturedRectangle":{"singleTextureOpacity":1,"textXHeight":0.39432539682539686,"textBaseline":0.80357104658134404,"isBackgroundTexture":true,"isVerticalText":false,"textColor":[0.32481390237808228,0.34466239809989929,0.37378150224685669,1],"textureType":6},"initialState":{"affineTransform":[1,0,0,1,0,0],"masksToBounds":false,"rotation":0,"scale":1,"position":{"pointX":168.49999999999994,"pointY":66.999999999999943},"width":331,"sublayerTransform":[1,0,0,0,0,1,0,0,0,0,1,0,0,0,0,1],"contentsRect":{"y":0,"x":0,"width":1,"height":1},"opacity":1,"edgeAntialiasingMask":0,"height":126,"hidden":false,"anchorPoint":{"pointX":0.5,"pointY":0.5}},"texture":"45FF1384BB6254CC61065789E45DDE73"}]}]},{"animations":[],"initialState":{"affineTransform":[1,0,0,1,0,0],"masksToBounds":false,"rotation":0,"scale":1,"position":{"pointX":960,"pointY":540},"width":1920,"sublayerTransform":[1,0,0,0,0,1,0,0,0,0,1,0,0,0,0,1],"contentsRect":{"y":0,"x":0,"width":1,"height":1},"opacity":1,"edgeAntialiasingMask":251658240,"height":1080,"hidden":false,"anchorPoint":{"pointX":0.5,"pointY":0.5}},"layers":[{"animations":[],"initialState":{"affineTransform":[1,0,0,1,0,0],"masksToBounds":false,"rotation":0,"scale":1,"position":{"pointX":592,"pointY":330.82199096679688},"width":994,"sublayerTransform":[1,0,0,0,0,1,0,0,0,0,1,0,0,0,0,1],"contentsRect":{"y":0,"x":0,"width":1,"height":1},"opacity":1,"edgeAntialiasingMask":251658240,"height":245,"hidden":false,"anchorPoint":{"pointX":0.5,"pointY":0.5}},"objectID":"7F028A4D-19D9-46BE-BBE2-3960A1D547CF","layers":[{"animations":[],"layers":[],"texturedRectangle":{"singleTextureOpacity":1,"textXHeight":0.48651162790697677,"textBaseline":0.7702784261038137,"isBackgroundTexture":false,"isVerticalText":false,"textColor":[0.32481390237808228,0.34466239809989929,0.37378150224685669,1],"textureType":6},"initialState":{"affineTransform":[1,0,0,1,0,0],"masksToBounds":false,"rotation":0,"scale":1,"position":{"pointX":283.5,"pointY":36.178009033203125},"width":555,"sublayerTransform":[1,0,0,0,0,1,0,0,0,0,1,0,0,0,0,1],"contentsRect":{"y":0,"x":0,"width":1,"height":1},"opacity":1,"edgeAntialiasingMask":0,"height":43,"hidden":false,"anchorPoint":{"pointX":0.5,"pointY":0.5}},"texture":"E1F6DBBADD9269EB94F2D6EDBB407B29"},{"animations":[],"layers":[],"texturedRectangle":{"singleTextureOpacity":1,"textXHeight":0.58111111111111113,"textBaseline":0.92005478673511076,"isBackgroundTexture":false,"isVerticalText":false,"textColor":[0.32481390237808228,0.34466239809989929,0.37378150224685669,1],"textureType":6},"initialState":{"affineTransform":[1,0,0,1,0,0],"masksToBounds":false,"rotation":0,"scale":1,"position":{"pointX":375,"pointY":133.67800903320312},"width":738,"sublayerTransform":[1,0,0,0,0,1,0,0,0,0,1,0,0,0,0,1],"contentsRect":{"y":0,"x":0,"width":1,"height":1},"opacity":1,"edgeAntialiasingMask":0,"height":36,"hidden":true,"anchorPoint":{"pointX":0.5,"pointY":0.5}},"texture":"07B1EF5E7DBD0FE096EBCD5BF0CB747D"},{"animations":[],"layers":[],"texturedRectangle":{"singleTextureOpacity":1,"textXHeight":0.48651162790697677,"textBaseline":0.7702784261038137,"isBackgroundTexture":false,"isVerticalText":false,"textColor":[0.32481390237808228,0.34466239809989929,0.37378150224685669,1],"textureType":6},"initialState":{"affineTransform":[1,0,0,1,0,0],"masksToBounds":false,"rotation":0,"scale":1,"position":{"pointX":521,"pointY":238.17800903320312},"width":958,"sublayerTransform":[1,0,0,0,0,1,0,0,0,0,1,0,0,0,0,1],"contentsRect":{"y":0,"x":0,"width":1,"height":1},"opacity":1,"edgeAntialiasingMask":0,"height":43,"hidden":true,"anchorPoint":{"pointX":0.5,"pointY":0.5}},"texture":"6882CA34338C7DA31EE83EDB94DF20A6"}]}]},{"animations":[],"initialState":{"affineTransform":[1,0,0,1,0,0],"masksToBounds":false,"rotation":0,"scale":1,"position":{"pointX":960,"pointY":540},"width":1920,"sublayerTransform":[1,0,0,0,0,1,0,0,0,0,1,0,0,0,0,1],"contentsRect":{"y":0,"x":0,"width":1,"height":1},"opacity":1,"edgeAntialiasingMask":251658240,"height":1080,"hidden":false,"anchorPoint":{"pointX":0.5,"pointY":0.5}},"layers":[{"animations":[],"initialState":{"affineTransform":[1,0,0,1,0,0],"masksToBounds":false,"rotation":0,"scale":1,"position":{"pointX":1867.0199754046334,"pointY":990.49998712539673},"width":25,"sublayerTransform":[1,0,0,0,0,1,0,0,0,0,1,0,0,0,0,1],"contentsRect":{"y":0,"x":0,"width":1,"height":1},"opacity":1,"edgeAntialiasingMask":251658240,"height":19,"hidden":false,"anchorPoint":{"pointX":0.5,"pointY":0.5}},"layers":[{"animations":[],"layers":[],"texturedRectangle":{"singleTextureOpacity":1,"textXHeight":0.55052631578947375,"textBaseline":0.91578830543317291,"isBackgroundTexture":true,"isVerticalText":false,"textColor":[0.32481390237808228,0.34466239809989929,0.37378150224685669,1],"textureType":6},"initialState":{"affineTransform":[1,0,0,1,0,0],"masksToBounds":false,"rotation":0,"scale":1,"position":{"pointX":15.980024595366558,"pointY":17.500012874603271},"width":25,"sublayerTransform":[1,0,0,0,0,1,0,0,0,0,1,0,0,0,0,1],"contentsRect":{"y":0,"x":0,"width":1,"height":1},"opacity":1,"edgeAntialiasingMask":0,"height":19,"hidden":false,"anchorPoint":{"pointX":0.5,"pointY":0.5}},"texture":"4E38E8EE8C81539C7C6B3F9891BFC9DE"}]}]}]}},{"effects":[{"beginTime":0,"baseLayer":{"animations":[],"initialState":{"affineTransform":[1,0,0,1,0,0],"masksToBounds":false,"rotation":0,"scale":1,"position":{"pointX":592,"pointY":330.82199096679688},"width":994,"sublayerTransform":[1,0,0,0,0,1,0,0,0,0,1,0,0,0,0,1],"contentsRect":{"y":0,"x":0,"width":1,"height":1},"opacity":1,"edgeAntialiasingMask":251658240,"height":245,"hidden":false,"anchorPoint":{"pointX":0.5,"pointY":0.5}},"objectID":"7F028A4D-19D9-46BE-BBE2-3960A1D547CF","layers":[{"animations":[],"layers":[],"texturedRectangle":{"singleTextureOpacity":1,"textXHeight":0.48651162790697677,"textBaseline":0.7702784261038137,"isBackgroundTexture":false,"isVerticalText":false,"textColor":[0.32481390237808228,0.34466239809989929,0.37378150224685669,1],"textureType":6},"initialState":{"affineTransform":[1,0,0,1,0,0],"masksToBounds":false,"rotation":0,"scale":1,"position":{"pointX":283.5,"pointY":36.178009033203125},"width":555,"sublayerTransform":[1,0,0,0,0,1,0,0,0,0,1,0,0,0,0,1],"contentsRect":{"y":0,"x":0,"width":1,"height":1},"opacity":1,"edgeAntialiasingMask":0,"height":43,"hidden":false,"anchorPoint":{"pointX":0.5,"pointY":0.5}},"texture":"E1F6DBBADD9269EB94F2D6EDBB407B29"},{"animations":[],"layers":[],"texturedRectangle":{"singleTextureOpacity":1,"textXHeight":0.58111111111111113,"textBaseline":0.92005478673511076,"isBackgroundTexture":false,"isVerticalText":false,"textColor":[0.32481390237808228,0.34466239809989929,0.37378150224685669,1],"textureType":6},"initialState":{"affineTransform":[1,0,0,1,0,0],"masksToBounds":false,"rotation":0,"scale":1,"position":{"pointX":375,"pointY":133.67800903320312},"width":738,"sublayerTransform":[1,0,0,0,0,1,0,0,0,0,1,0,0,0,0,1],"contentsRect":{"y":0,"x":0,"width":1,"height":1},"opacity":1,"edgeAntialiasingMask":0,"height":36,"hidden":false,"anchorPoint":{"pointX":0.5,"pointY":0.5}},"texture":"07B1EF5E7DBD0FE096EBCD5BF0CB747D"},{"animations":[],"initialState":{"affineTransform":[1,0,0,1,0,0],"masksToBounds":false,"rotation":0,"scale":1,"position":{"pointX":865,"pointY":331.67800903320312},"width":994,"sublayerTransform":[1,0,0,0,0,1,0,0,0,0,1,-0.00035007912466775983,0,0,0,1],"contentsRect":{"y":0,"x":0,"width":1,"height":1},"opacity":1,"edgeAntialiasingMask":251658240,"height":245,"hidden":false,"anchorPoint":{"pointX":0.87022132796780682,"pointY":1.3537877919722576}},"layers":[{"animations":[{"additive":false,"timeOffset":0,"beginTime":1e-100,"repeatCount":0,"fillMode":"both","duration":0.001,"autoreverses":false,"animations":[{"additive":false,"timeOffset":0,"beginTime":0,"from":{"scalar":true},"repeatCount":0,"fillMode":"both","duration":0.0001,"autoreverses":false,"property":"hidden","to":{"scalar":false},"removedOnCompletion":true},{"additive":false,"timeOffset":0,"beginTime":0.0001,"from":{"scalar":false},"repeatCount":0,"fillMode":"forwards","duration":0.00089999999999999998,"autoreverses":false,"property":"hidden","to":{"scalar":false},"removedOnCompletion":true}],"removedOnCompletion":false}],"layers":[],"texturedRectangle":{"singleTextureOpacity":1,"textXHeight":0.48651162790697677,"textBaseline":0.7702784261038137,"isBackgroundTexture":false,"isVerticalText":false,"textColor":[0.32481390237808228,0.34466239809989929,0.37378150224685669,1],"textureType":6},"initialState":{"affineTransform":[1,0,0,1,0,0],"masksToBounds":false,"rotation":0,"scale":1,"position":{"pointX":521,"pointY":238.17800903320312},"width":958,"sublayerTransform":[1,0,0,0,0,1,0,0,0,0,1,0,0,0,0,1],"contentsRect":{"y":0,"x":0,"width":1,"height":1},"opacity":1,"edgeAntialiasingMask":0,"height":43,"hidden":true,"anchorPoint":{"pointX":0.5,"pointY":0.5}},"texture":"6882CA34338C7DA31EE83EDB94DF20A6"}]}]},"effects":[],"duration":0.001,"type":"buildIn","attributes":{"direction":0},"name":"apple:bc-appear","objectID":"7F028A4D-19D9-46BE-BBE2-3960A1D547CF"}],"automaticPlay":false,"hyperlinks":[],"accessibility":[{"text":"￼","targetRectangle":{"y":984.99998712539673,"x":1859.5199754046334,"width":22.079999999999927,"height":25.799999594688416}},{"text":"￼ Tests","targetRectangle":{"y":54,"x":99,"width":333.22888560421768,"height":124.04999807476997}},{"text":"pasted-movie.png","targetRectangle":{"y":55.249951869249344,"x":99,"width":88.888885498046875,"height":100}}],"baseLayer":{"animations":[],"initialState":{"affineTransform":[1,0,0,1,0,0],"masksToBounds":false,"rotation":0,"scale":1,"position":{"pointX":960,"pointY":540},"width":1920,"sublayerTransform":[1,0,0,0,0,1,0,0,0,0,1,0,0,0,0,1],"contentsRect":{"y":0,"x":0,"width":1,"height":1},"opacity":1,"edgeAntialiasingMask":251658240,"height":1080,"hidden":false,"anchorPoint":{"pointX":0.5,"pointY":0.5}},"layers":[{"animations":[],"initialState":{"affineTransform":[1,0,0,1,0,0],"masksToBounds":false,"rotation":0,"scale":1,"position":{"pointX":960,"pointY":540},"width":1920,"sublayerTransform":[1,0,0,0,0,1,0,0,0,0,1,0,0,0,0,1],"contentsRect":{"y":0,"x":0,"width":1,"height":1},"opacity":1,"edgeAntialiasingMask":251658240,"height":1080,"hidden":false,"anchorPoint":{"pointX":0.5,"pointY":0.5}},"layers":[{"animations":[],"initialState":{"affineTransform":[1,0,0,1,0,0],"masksToBounds":false,"rotation":0,"scale":1,"position":{"pointX":960,"pointY":540},"width":1920,"sublayerTransform":[1,0,0,0,0,1,0,0,0,0,1,0,0,0,0,1],"contentsRect":{"y":0,"x":0,"width":1,"height":1},"opacity":1,"edgeAntialiasingMask":251658240,"height":1080,"hidden":false,"anchorPoint":{"pointX":0.5,"pointY":0.5}},"layers":[{"animations":[],"layers":[],"texturedRectangle":{"isBackgroundTexture":true,"singleTextureOpacity":1,"textureType":1,"textBaseline":0,"textXHeight":0,"isVerticalText":false},"initialState":{"affineTransform":[1,0,0,1,0,0],"masksToBounds":false,"rotation":0,"scale":1,"position":{"pointX":960,"pointY":540},"width":1920,"sublayerTransform":[1,0,0,0,0,1,0,0,0,0,1,0,0,0,0,1],"contentsRect":{"y":0,"x":0,"width":1,"height":1},"opacity":1,"edgeAntialiasingMask":0,"height":1080,"hidden":false,"anchorPoint":{"pointX":0.5,"pointY":0.5}},"texture":"F9A0A76BAF2A9879A1DAA8312FE7E552"}]}]},{"animations":[],"initialState":{"affineTransform":[1,0,0,1,0,0],"masksToBounds":false,"rotation":0,"scale":1,"position":{"pointX":960,"pointY":540},"width":1920,"sublayerTransform":[1,0,0,0,0,1,0,0,0,0,1,0,0,0,0,1],"contentsRect":{"y":0,"x":0,"width":1,"height":1},"opacity":1,"edgeAntialiasingMask":251658240,"height":1080,"hidden":false,"anchorPoint":{"pointX":0.5,"pointY":0.5}},"layers":[{"animations":[],"initialState":{"affineTransform":[1,0,0,1,0,0],"masksToBounds":false,"rotation":0,"scale":1,"position":{"pointX":260.50000000000006,"pointY":113.00000000000006},"width":331,"sublayerTransform":[1,0,0,0,0,1,0,0,0,0,1,0,0,0,0,1],"contentsRect":{"y":0,"x":0,"width":1,"height":1},"opacity":1,"edgeAntialiasingMask":251658240,"height":126,"hidden":false,"anchorPoint":{"pointX":0.5,"pointY":0.5}},"layers":[{"animations":[],"layers":[],"texturedRectangle":{"singleTextureOpacity":1,"textXHeight":0.39432539682539686,"textBaseline":0.80357104658134404,"isBackgroundTexture":true,"isVerticalText":false,"textColor":[0.32481390237808228,0.34466239809989929,0.37378150224685669,1],"textureType":6},"initialState":{"affineTransform":[1,0,0,1,0,0],"masksToBounds":false,"rotation":0,"scale":1,"position":{"pointX":168.49999999999994,"pointY":66.999999999999943},"width":331,"sublayerTransform":[1,0,0,0,0,1,0,0,0,0,1,0,0,0,0,1],"contentsRect":{"y":0,"x":0,"width":1,"height":1},"opacity":1,"edgeAntialiasingMask":0,"height":126,"hidden":false,"anchorPoint":{"pointX":0.5,"pointY":0.5}},"texture":"45FF1384BB6254CC61065789E45DDE73"}]}]},{"animations":[],"initialState":{"affineTransform":[1,0,0,1,0,0],"masksToBounds":false,"rotation":0,"scale":1,"position":{"pointX":960,"pointY":540},"width":1920,"sublayerTransform":[1,0,0,0,0,1,0,0,0,0,1,0,0,0,0,1],"contentsRect":{"y":0,"x":0,"width":1,"height":1},"opacity":1,"edgeAntialiasingMask":251658240,"height":1080,"hidden":false,"anchorPoint":{"pointX":0.5,"pointY":0.5}},"layers":[{"animations":[],"initialState":{"affineTransform":[1,0,0,1,0,0],"masksToBounds":false,"rotation":0,"scale":1,"position":{"pointX":592,"pointY":330.82199096679688},"width":994,"sublayerTransform":[1,0,0,0,0,1,0,0,0,0,1,0,0,0,0,1],"contentsRect":{"y":0,"x":0,"width":1,"height":1},"opacity":1,"edgeAntialiasingMask":251658240,"height":245,"hidden":false,"anchorPoint":{"pointX":0.5,"pointY":0.5}},"objectID":"7F028A4D-19D9-46BE-BBE2-3960A1D547CF","layers":[{"animations":[],"layers":[],"texturedRectangle":{"singleTextureOpacity":1,"textXHeight":0.48651162790697677,"textBaseline":0.7702784261038137,"isBackgroundTexture":false,"isVerticalText":false,"textColor":[0.32481390237808228,0.34466239809989929,0.37378150224685669,1],"textureType":6},"initialState":{"affineTransform":[1,0,0,1,0,0],"masksToBounds":false,"rotation":0,"scale":1,"position":{"pointX":283.5,"pointY":36.178009033203125},"width":555,"sublayerTransform":[1,0,0,0,0,1,0,0,0,0,1,0,0,0,0,1],"contentsRect":{"y":0,"x":0,"width":1,"height":1},"opacity":1,"edgeAntialiasingMask":0,"height":43,"hidden":false,"anchorPoint":{"pointX":0.5,"pointY":0.5}},"texture":"E1F6DBBADD9269EB94F2D6EDBB407B29"},{"animations":[],"layers":[],"texturedRectangle":{"singleTextureOpacity":1,"textXHeight":0.58111111111111113,"textBaseline":0.92005478673511076,"isBackgroundTexture":false,"isVerticalText":false,"textColor":[0.32481390237808228,0.34466239809989929,0.37378150224685669,1],"textureType":6},"initialState":{"affineTransform":[1,0,0,1,0,0],"masksToBounds":false,"rotation":0,"scale":1,"position":{"pointX":375,"pointY":133.67800903320312},"width":738,"sublayerTransform":[1,0,0,0,0,1,0,0,0,0,1,0,0,0,0,1],"contentsRect":{"y":0,"x":0,"width":1,"height":1},"opacity":1,"edgeAntialiasingMask":0,"height":36,"hidden":false,"anchorPoint":{"pointX":0.5,"pointY":0.5}},"texture":"07B1EF5E7DBD0FE096EBCD5BF0CB747D"},{"animations":[],"layers":[],"texturedRectangle":{"singleTextureOpacity":1,"textXHeight":0.48651162790697677,"textBaseline":0.7702784261038137,"isBackgroundTexture":false,"isVerticalText":false,"textColor":[0.32481390237808228,0.34466239809989929,0.37378150224685669,1],"textureType":6},"initialState":{"affineTransform":[1,0,0,1,0,0],"masksToBounds":false,"rotation":0,"scale":1,"position":{"pointX":521,"pointY":238.17800903320312},"width":958,"sublayerTransform":[1,0,0,0,0,1,0,0,0,0,1,0,0,0,0,1],"contentsRect":{"y":0,"x":0,"width":1,"height":1},"opacity":1,"edgeAntialiasingMask":0,"height":43,"hidden":true,"anchorPoint":{"pointX":0.5,"pointY":0.5}},"texture":"6882CA34338C7DA31EE83EDB94DF20A6"}]}]},{"animations":[],"initialState":{"affineTransform":[1,0,0,1,0,0],"masksToBounds":false,"rotation":0,"scale":1,"position":{"pointX":960,"pointY":540},"width":1920,"sublayerTransform":[1,0,0,0,0,1,0,0,0,0,1,0,0,0,0,1],"contentsRect":{"y":0,"x":0,"width":1,"height":1},"opacity":1,"edgeAntialiasingMask":251658240,"height":1080,"hidden":false,"anchorPoint":{"pointX":0.5,"pointY":0.5}},"layers":[{"animations":[],"initialState":{"affineTransform":[1,0,0,1,0,0],"masksToBounds":false,"rotation":0,"scale":1,"position":{"pointX":1867.0199754046334,"pointY":990.49998712539673},"width":25,"sublayerTransform":[1,0,0,0,0,1,0,0,0,0,1,0,0,0,0,1],"contentsRect":{"y":0,"x":0,"width":1,"height":1},"opacity":1,"edgeAntialiasingMask":251658240,"height":19,"hidden":false,"anchorPoint":{"pointX":0.5,"pointY":0.5}},"layers":[{"animations":[],"layers":[],"texturedRectangle":{"singleTextureOpacity":1,"textXHeight":0.55052631578947375,"textBaseline":0.91578830543317291,"isBackgroundTexture":true,"isVerticalText":false,"textColor":[0.32481390237808228,0.34466239809989929,0.37378150224685669,1],"textureType":6},"initialState":{"affineTransform":[1,0,0,1,0,0],"masksToBounds":false,"rotation":0,"scale":1,"position":{"pointX":15.980024595366558,"pointY":17.500012874603271},"width":25,"sublayerTransform":[1,0,0,0,0,1,0,0,0,0,1,0,0,0,0,1],"contentsRect":{"y":0,"x":0,"width":1,"height":1},"opacity":1,"edgeAntialiasingMask":0,"height":19,"hidden":false,"anchorPoint":{"pointX":0.5,"pointY":0.5}},"texture":"4E38E8EE8C81539C7C6B3F9891BFC9DE"}]}]}]}},{"effects":[{"beginTime":0,"baseLayer":{"animations":[],"initialState":{"affineTransform":[1,0,0,1,0,0],"masksToBounds":false,"rotation":0,"scale":1,"position":{"pointX":960,"pointY":540},"width":1920,"sublayerTransform":[1,0,0,0,0,1,0,0,0,0,1,0,0,0,0,1],"contentsRect":{"y":0,"x":0,"width":1,"height":1},"opacity":1,"edgeAntialiasingMask":251658240,"height":1080,"hidden":false,"anchorPoint":{"pointX":0.5,"pointY":0.5}},"objectID":"0","layers":[{"animations":[],"initialState":{"affineTransform":[1,0,0,1,0,0],"masksToBounds":false,"rotation":0,"scale":1,"position":{"pointX":960,"pointY":540},"width":1920,"sublayerTransform":[1,0,0,0,0,1,0,0,0,0,1,-0.00035007912466775983,0,0,0,1],"contentsRect":{"y":0,"x":0,"width":1,"height":1},"opacity":1,"edgeAntialiasingMask":251658240,"height":1080,"hidden":false,"anchorPoint":{"pointX":0.5,"pointY":0.5}},"layers":[{"animations":[],"layers":[],"texturedRectangle":{"isBackgroundTexture":false,"singleTextureOpacity":1,"textureType":0,"textBaseline":0,"textXHeight":0,"isVerticalText":false},"initialState":{"affineTransform":[1,0,0,1,0,0],"masksToBounds":false,"rotation":0,"scale":1,"position":{"pointX":960,"pointY":540},"width":1920,"sublayerTransform":[1,0,0,0,0,1,0,0,0,0,1,0,0,0,0,1],"contentsRect":{"y":0,"x":0,"width":1,"height":1},"opacity":1,"edgeAntialiasingMask":0,"height":1080,"hidden":false,"anchorPoint":{"pointX":0.5,"pointY":0.5}},"texture":"103FD9B870C485FA2C10AF83D6AA848C"},{"animations":[{"additive":false,"timeOffset":0,"beginTime":0,"from":{"scalar":false},"repeatCount":0,"fillMode":"both","duration":0.001,"autoreverses":false,"property":"hidden","to":{"scalar":true},"removedOnCompletion":false}],"layers":[],"texturedRectangle":{"isBackgroundTexture":false,"singleTextureOpacity":1,"textureType":0,"textBaseline":0,"textXHeight":0,"isVerticalText":false},"initialState":{"affineTransform":[1,0,0,1,0,0],"masksToBounds":false,"rotation":0,"scale":1,"position":{"pointX":960,"pointY":540},"width":1920,"sublayerTransform":[1,0,0,0,0,1,0,0,0,0,1,0,0,0,0,1],"contentsRect":{"y":0,"x":0,"width":1,"height":1},"opacity":1,"edgeAntialiasingMask":0,"height":1080,"hidden":false,"anchorPoint":{"pointX":0.5,"pointY":0.5}},"texture":"3E7AC91706FC8DE5080498FF81185346"}]}]},"effects":[],"duration":0.001,"type":"transition","attributes":{"direction":0},"name":"none","objectID":"0"}],"automaticPlay":false,"hyperlinks":[],"accessibility":[{"text":"Requires good test coverage","targetRectangle":{"y":212.32199096679688,"x":134.99999904632568,"width":521.36000000000001,"height":52.599999189376831}},{"text":"Tests tend to cover intended use cases","targetRectangle":{"y":265.32199096679688,"x":134.99999904632568,"width":704.60000000000014,"height":100.59999918937683}},{"text":"Or reported (and already fixed) issues (regressions)","targetRectangle":{"y":366.32199096679688,"x":170.99999904632568,"width":924.24000000000024,"height":100.59999918937683}},{"text":"￼","targetRectangle":{"y":984.99998712539673,"x":1859.5199754046334,"width":22.079999999999927,"height":25.799999594688416}},{"text":"￼ Tests","targetRectangle":{"y":54,"x":99,"width":333.22888560421768,"height":124.04999807476997}},{"text":"pasted-movie.png","targetRectangle":{"y":55.249951869249344,"x":99,"width":88.888885498046875,"height":100}}],"baseLayer":{"animations":[],"initialState":{"affineTransform":[1,0,0,1,0,0],"masksToBounds":false,"rotation":0,"scale":1,"position":{"pointX":960,"pointY":540},"width":1920,"sublayerTransform":[1,0,0,0,0,1,0,0,0,0,1,0,0,0,0,1],"contentsRect":{"y":0,"x":0,"width":1,"height":1},"opacity":1,"edgeAntialiasingMask":251658240,"height":1080,"hidden":false,"anchorPoint":{"pointX":0.5,"pointY":0.5}},"objectID":"0","layers":[{"animations":[],"initialState":{"affineTransform":[1,0,0,1,0,0],"masksToBounds":false,"rotation":0,"scale":1,"position":{"pointX":960,"pointY":540},"width":1920,"sublayerTransform":[1,0,0,0,0,1,0,0,0,0,1,-0.00035007912466775983,0,0,0,1],"contentsRect":{"y":0,"x":0,"width":1,"height":1},"opacity":1,"edgeAntialiasingMask":251658240,"height":1080,"hidden":false,"anchorPoint":{"pointX":0.5,"pointY":0.5}},"layers":[{"animations":[],"layers":[],"texturedRectangle":{"isBackgroundTexture":false,"singleTextureOpacity":1,"textureType":0,"textBaseline":0,"textXHeight":0,"isVerticalText":false},"initialState":{"affineTransform":[1,0,0,1,0,0],"masksToBounds":false,"rotation":0,"scale":1,"position":{"pointX":960,"pointY":540},"width":1920,"sublayerTransform":[1,0,0,0,0,1,0,0,0,0,1,0,0,0,0,1],"contentsRect":{"y":0,"x":0,"width":1,"height":1},"opacity":1,"edgeAntialiasingMask":0,"height":1080,"hidden":false,"anchorPoint":{"pointX":0.5,"pointY":0.5}},"texture":"3E7AC91706FC8DE5080498FF81185346"}]}]}}]}